Workbook

Sheet Summary
A1: Subject | B1: Subtopics | C1: Pearl listings | D1: Unique pearls | E1: Cross-listed pearls
A2: Anatomy | B2: =COUNTIFS('All Pearls'!$A$2:$A$2690,A2,'All Pearls'!$H$2:$H$2690,1) -> 10 | C2: =COUNTIF('All Pearls'!$A$2:$A$2690,A2) -> 173 | D2: =COUNTIFS('All Pearls'!$A$2:$A$2690,A2,'All Pearls'!$G$2:$G$2690,1) -> 168 | E2: =C2-D2 -> 5
A3: Physiology | B3: =COUNTIFS('All Pearls'!$A$2:$A$2690,A3,'All Pearls'!$H$2:$H$2690,1) -> 12 | C3: =COUNTIF('All Pearls'!$A$2:$A$2690,A3) -> 208 | D3: =COUNTIFS('All Pearls'!$A$2:$A$2690,A3,'All Pearls'!$G$2:$G$2690,1) -> 206 | E3: =C3-D3 -> 2
A4: Biochemistry | B4: =COUNTIFS('All Pearls'!$A$2:$A$2690,A4,'All Pearls'!$H$2:$H$2690,1) -> 11 | C4: =COUNTIF('All Pearls'!$A$2:$A$2690,A4) -> 139 | D4: =COUNTIFS('All Pearls'!$A$2:$A$2690,A4,'All Pearls'!$G$2:$G$2690,1) -> 132 | E4: =C4-D4 -> 7
A5: Pathology | B5: =COUNTIFS('All Pearls'!$A$2:$A$2690,A5,'All Pearls'!$H$2:$H$2690,1) -> 12 | C5: =COUNTIF('All Pearls'!$A$2:$A$2690,A5) -> 257 | D5: =COUNTIFS('All Pearls'!$A$2:$A$2690,A5,'All Pearls'!$G$2:$G$2690,1) -> 255 | E5: =C5-D5 -> 2
A6: Pharmacology | B6: =COUNTIFS('All Pearls'!$A$2:$A$2690,A6,'All Pearls'!$H$2:$H$2690,1) -> 13 | C6: =COUNTIF('All Pearls'!$A$2:$A$2690,A6) -> 143 | D6: =COUNTIFS('All Pearls'!$A$2:$A$2690,A6,'All Pearls'!$G$2:$G$2690,1) -> 142 | E6: =C6-D6 -> 1
A7: Forensic Medicine | B7: =COUNTIFS('All Pearls'!$A$2:$A$2690,A7,'All Pearls'!$H$2:$H$2690,1) -> 10 | C7: =COUNTIF('All Pearls'!$A$2:$A$2690,A7) -> 93 | D7: =COUNTIFS('All Pearls'!$A$2:$A$2690,A7,'All Pearls'!$G$2:$G$2690,1) -> 93 | E7: =C7-D7 -> 0
A8: Community Medicine | B8: =COUNTIFS('All Pearls'!$A$2:$A$2690,A8,'All Pearls'!$H$2:$H$2690,1) -> 22 | C8: =COUNTIF('All Pearls'!$A$2:$A$2690,A8) -> 236 | D8: =COUNTIFS('All Pearls'!$A$2:$A$2690,A8,'All Pearls'!$G$2:$G$2690,1) -> 233 | E8: =C8-D8 -> 3
A9: ENT | B9: =COUNTIFS('All Pearls'!$A$2:$A$2690,A9,'All Pearls'!$H$2:$H$2690,1) -> 6 | C9: =COUNTIF('All Pearls'!$A$2:$A$2690,A9) -> 90 | D9: =COUNTIFS('All Pearls'!$A$2:$A$2690,A9,'All Pearls'!$G$2:$G$2690,1) -> 89 | E9: =C9-D9 -> 1
A10: Ophthalmology | B10: =COUNTIFS('All Pearls'!$A$2:$A$2690,A10,'All Pearls'!$H$2:$H$2690,1) -> 12 | C10: =COUNTIF('All Pearls'!$A$2:$A$2690,A10) -> 76 | D10: =COUNTIFS('All Pearls'!$A$2:$A$2690,A10,'All Pearls'!$G$2:$G$2690,1) -> 70 | E10: =C10-D10 -> 6
A11: Medicine | B11: =COUNTIFS('All Pearls'!$A$2:$A$2690,A11,'All Pearls'!$H$2:$H$2690,1) -> 14 | C11: =COUNTIF('All Pearls'!$A$2:$A$2690,A11) -> 365 | D11: =COUNTIFS('All Pearls'!$A$2:$A$2690,A11,'All Pearls'!$G$2:$G$2690,1) -> 359 | E11: =C11-D11 -> 6
A12: Surgery | B12: =COUNTIFS('All Pearls'!$A$2:$A$2690,A12,'All Pearls'!$H$2:$H$2690,1) -> 18 | C12: =COUNTIF('All Pearls'!$A$2:$A$2690,A12) -> 276 | D12: =COUNTIFS('All Pearls'!$A$2:$A$2690,A12,'All Pearls'!$G$2:$G$2690,1) -> 271 | E12: =C12-D12 -> 5
A13: Obstetrics & Gynaecology | B13: =COUNTIFS('All Pearls'!$A$2:$A$2690,A13,'All Pearls'!$H$2:$H$2690,1) -> 11 | C13: =COUNTIF('All Pearls'!$A$2:$A$2690,A13) -> 129 | D13: =COUNTIFS('All Pearls'!$A$2:$A$2690,A13,'All Pearls'!$G$2:$G$2690,1) -> 128 | E13: =C13-D13 -> 1
... A19: Radiology | B19: =COUNTIFS('All Pearls'!$A$2:$A$2690,A19,'All Pearls'!$H$2:$H$2690,1) -> 5 | C19: =COUNTIF('All Pearls'!$A$2:$A$2690,A19) -> 40 | D19: =COUNTIFS('All Pearls'!$A$2:$A$2690,A19,'All Pearls'!$G$2:$G$2690,1) -> 40 | E19: =C19-D19 -> 0
A20: Total | B20: =SUM(B2:B19) -> 222 | C20: =SUM(C2:C19) -> 2689 | D20: =SUM(D2:D19) -> 2618 | E20: =SUM(E2:E19) -> 71
A22: Source: the 18 subject screenshots in this repository, read with OCR and checked by hand at the stitching seams.
A23: "Pearl listings" counts every row; a pearl filed under two subtopics of one subject counts twice there and once in "Unique pearls".
A24: A few titles were cut off at the bottom of a screenshot and completed by hand; those rows carry a note in the All Pearls tab.
A25: Each subject list is complete: no pearls follow the last one shown in its screenshot.

Sheet All Pearls
A1: Subject | B1: Subtopic | C1: Pearl ID | D1: Pearl | E1: Also listed under | F1: Note | G1: First in subject? | H1: First in subtopic?
A2: Anatomy | B2: Embryology | C2: PM2509 | D2: Upper Limb Nerve Injuries | G2: =IF(COUNTIFS($A$2:A2,A2,$C$2:C2,C2)=1,1,0) -> 1 | H2: =IF(COUNTIFS($A$2:A2,A2,$B$2:B2,B2)=1,1,0) -> 1
A3: Anatomy | B3: Embryology | C3: PM2393 | D3: Derivatives of Mesoderm | G3: =IF(COUNTIFS($A$2:A3,A3,$C$2:C3,C3)=1,1,0) -> 1 | H3: =IF(COUNTIFS($A$2:A3,A3,$B$2:B3,B3)=1,1,0) -> 0
A4: Anatomy | B4: Embryology | C4: PM2351 | D4: Embryology of the ear | G4: =IF(COUNTIFS($A$2:A4,A4,$C$2:C4,C4)=1,1,0) -> 1 | H4: =IF(COUNTIFS($A$2:A4,A4,$B$2:B4,B4)=1,1,0) -> 0
A5: Anatomy | B5: Embryology | C5: PM2348 | D5: Homologous structures in male and female genitalia | G5: =IF(COUNTIFS($A$2:A5,A5,$C$2:C5,C5)=1,1,0) -> 1 | H5: =IF(COUNTIFS($A$2:A5,A5,$B$2:B5,B5)=1,1,0) -> 0
A6: Anatomy | B6: Embryology | C6: PM2236 | D6: Twinning | G6: =IF(COUNTIFS($A$2:A6,A6,$C$2:C6,C6)=1,1,0) -> 1 | H6: =IF(COUNTIFS($A$2:A6,A6,$B$2:B6,B6)=1,1,0) -> 0
A7: Anatomy | B7: Embryology | C7: PM2028 | D7: Concepts of Fetal Circulation | G7: =IF(COUNTIFS($A$2:A7,A7,$C$2:C7,C7)=1,1,0) -> 1 | H7: =IF(COUNTIFS($A$2:A7,A7,$B$2:B7,B7)=1,1,0) -> 0
A8: Anatomy | B8: Embryology | C8: PM1979 | D8: Derivatives of Mesonephric (Wolffian) duct and Paramesonephric (Mullerian) duct | G8: =IF(COUNTIFS($A$2:A8,A8,$C$2:C8,C8)=1,1,0) -> 1 | H8: =IF(COUNTIFS($A$2:A8,A8,$B$2:B8,B8)=1,1,0) -> 0
A9: Anatomy | B9: Embryology | C9: PM1974 | D9: Neural crest derivatives | G9: =IF(COUNTIFS($A$2:A9,A9,$C$2:C9,C9)=1,1,0) -> 1 | H9: =IF(COUNTIFS($A$2:A9,A9,$B$2:B9,B9)=1,1,0) -> 0
A10: Anatomy | B10: Embryology | C10: PM1888 | D10: Summary of ocular embryogenesis | G10: =IF(COUNTIFS($A$2:A10,A10,$C$2:C10,C10)=1,1,0) -> 1 | H10: =IF(COUNTIFS($A$2:A10,A10,$B$2:B10,B10)=1,1,0) -> 0
A11: Anatomy | B11: Embryology | C11: PM1239 | D11: Embryological derivatives of the eye | G11: =IF(COUNTIFS($A$2:A11,A11,$C$2:C11,C11)=1,1,0) -> 1 | H11: =IF(COUNTIFS($A$2:A11,A11,$B$2:B11,B11)=1,1,0) -> 0
A12: Anatomy | B12: Embryology | C12: PM1215 | D12: Locations of Congenital Heart Disease | G12: =IF(COUNTIFS($A$2:A12,A12,$C$2:C12,C12)=1,1,0) -> 1 | H12: =IF(COUNTIFS($A$2:A12,A12,$B$2:B12,B12)=1,1,0) -> 0
A13: Anatomy | B13: Embryology | C13: PM1065 | D13: Difference between gastroschisis and omphalocele | G13: =IF(COUNTIFS($A$2:A13,A13,$C$2:C13,C13)=1,1,0) -> 1 | H13: =IF(COUNTIFS($A$2:A13,A13,$B$2:B13,B13)=1,1,0) -> 0
... A25: Anatomy | B25: Embryology | C25: PM0177 | D25: Tissue Stem Cells and their Location | G25: =IF(COUNTIFS($A$2:A25,A25,$C$2:C25,C25)=1,1,0) -> 1 | H25: =IF(COUNTIFS($A$2:A25,A25,$B$2:B25,B25)=1,1,0) -> 0
A26: Anatomy | B26: Histology | C26: PM2250 | D26: Layers of the cerebellar cortex | E26: Neuroanatomy | G26: =IF(COUNTIFS($A$2:A26,A26,$C$2:C26,C26)=1,1,0) -> 1 | H26: =IF(COUNTIFS($A$2:A26,A26,$B$2:B26,B26)=1,1,0) -> 1
A27: Anatomy | B27: Histology | C27: PM2248 | D27: Layers of Cerebral Cortex | E27: Neuroanatomy | G27: =IF(COUNTIFS($A$2:A27,A27,$C$2:C27,C27)=1,1,0) -> 1 | H27: =IF(COUNTIFS($A$2:A27,A27,$B$2:B27,B27)=1,1,0) -> 0
A28: Anatomy | B28: Histology | C28: PM1880 | D28: Cells of the epidermis | G28: =IF(COUNTIFS($A$2:A28,A28,$C$2:C28,C28)=1,1,0) -> 1 | H28: =IF(COUNTIFS($A$2:A28,A28,$B$2:B28,B28)=1,1,0) -> 0
A29: Anatomy | B29: Histology | C29: PM1075 | D29: Various Types of Exocrine Glands with Examples | G29: =IF(COUNTIFS($A$2:A29,A29,$C$2:C29,C29)=1,1,0) -> 1 | H29: =IF(COUNTIFS($A$2:A29,A29,$B$2:B29,B29)=1,1,0) -> 0
A30: Anatomy | B30: Histology | C30: PM1071 | D30: Various Types of Epithelium, Their Location and Functions | G30: =IF(COUNTIFS($A$2:A30,A30,$C$2:C30,C30)=1,1,0) -> 1 | H30: =IF(COUNTIFS($A$2:A30,A30,$B$2:B30,B30)=1,1,0) -> 0
A31: Anatomy | B31: Histology | C31: PM0709 | D31: Comparison between Types of Sweat Glands | G31: =IF(COUNTIFS($A$2:A31,A31,$C$2:C31,C31)=1,1,0) -> 1 | H31: =IF(COUNTIFS($A$2:A31,A31,$B$2:B31,B31)=1,1,0) -> 0
A32: Anatomy | B32: Histology | C32: PM0706 | D32: Microanatomy of Muscle Fibres | G32: =IF(COUNTIFS($A$2:A32,A32,$C$2:C32,C32)=1,1,0) -> 1 | H32: =IF(COUNTIFS($A$2:A32,A32,$B$2:B32,B32)=1,1,0) -> 0
A33: Anatomy | B33: Abdomen and Pelvis | C33: PM2366 | D33: Perineal Body | G33: =IF(COUNTIFS($A$2:A33,A33,$C$2:C33,C33)=1,1,0) -> 1 | H33: =IF(COUNTIFS($A$2:A33,A33,$B$2:B33,B33)=1,1,0) -> 1
A34: Anatomy | B34: Abdomen and Pelvis | C34: PM2282 | D34: Gluteal Muscles | G34: =IF(COUNTIFS($A$2:A34,A34,$C$2:C34,C34)=1,1,0) -> 1 | H34: =IF(COUNTIFS($A$2:A34,A34,$B$2:B34,B34)=1,1,0) -> 0
A35: Anatomy | B35: Abdomen and Pelvis | C35: PM2281 | D35: Sciatic nerve divisions and supply | E35: Lower Limb | G35: =IF(COUNTIFS($A$2:A35,A35,$C$2:C35,C35)=1,1,0) -> 1 | H35: =IF(COUNTIFS($A$2:A35,A35,$B$2:B35,B35)=1,1,0) -> 0
A36: Anatomy | B36: Abdomen and Pelvis | C36: PM2280 | D36: Various muscles of the gluteal region and their innervation | G36: =IF(COUNTIFS($A$2:A36,A36,$C$2:C36,C36)=1,1,0) -> 1 | H36: =IF(COUNTIFS($A$2:A36,A36,$B$2:B36,B36)=1,1,0) -> 0
A37: Anatomy | B37: Abdomen and Pelvis | C37: PM2214 | D37: Lymphatic drainage of pelvic structures | G37: =IF(COUNTIFS($A$2:A37,A37,$C$2:C37,C37)=1,1,0) -> 1 | H37: =IF(COUNTIFS($A$2:A37,A37,$B$2:B37,B37)=1,1,0) -> 0
A38: Anatomy | B38: Abdomen and Pelvis | C38: PM2080 | D38: Calot's triangle and Hepatocystic triangle | G38: =IF(COUNTIFS($A$2:A38,A38,$C$2:C38,C38)=1,1,0) -> 1 | H38: =IF(COUNTIFS($A$2:A38,A38,$B$2:B38,B38)=1,1,0) -> 0
A39: Anatomy | B39: Abdomen and Pelvis | C39: PM2078 | D39: Common sites of porto-systemic anastomosis in portal hypertension | G39: =IF(COUNTIFS($A$2:A39,A39,$C$2:C39,C39)=1,1,0) -> 1 | H39: =IF(COUNTIFS($A$2:A39,A39,$B$2:B39,B39)=1,1,0) -> 0
A40: Anatomy | B40: Abdomen and Pelvis | C40: PM1851 | D40: Fallopian tube | G40: =IF(COUNTIFS($A$2:A40,A40,$C$2:C40,C40)=1,1,0) -> 1 | H40: =IF(COUNTIFS($A$2:A40,A40,$B$2:B40,B40)=1,1,0) -> 0
A41: Anatomy | B41: Abdomen and Pelvis | C41: PM1580 | D41: Characteristic differentiating features of the jejunum and ileum | G41: =IF(COUNTIFS($A$2:A41,A41,$C$2:C41,C41)=1,1,0) -> 1 | H41: =IF(COUNTIFS($A$2:A41,A41,$B$2:B41,B41)=1,1,0) -> 0
A42: Anatomy | B42: Abdomen and Pelvis | C42: PM1371 | D42: Passaro’s Triangle | G42: =IF(COUNTIFS($A$2:A42,A42,$C$2:C42,C42)=1,1,0) -> 1 | H42: =IF(COUNTIFS($A$2:A42,A42,$B$2:B42,B42)=1,1,0) -> 0
A43: Anatomy | B43: Abdomen and Pelvis | C43: PM1352 | D43: Nerve supply in the pelvis | G43: =IF(COUNTIFS($A$2:A43,A43,$C$2:C43,C43)=1,1,0) -> 1 | H43: =IF(COUNTIFS($A$2:A43,A43,$B$2:B43,B43)=1,1,0) -> 0
A44: Anatomy | B44: Abdomen and Pelvis | C44: PM1351 | D44: Contents of the Broad ligament | G44: =IF(COUNTIFS($A$2:A44,A44,$C$2:C44,C44)=1,1,0) -> 1 | H44: =IF(COUNTIFS($A$2:A44,A44,$B$2:B44,B44)=1,1,0) -> 0
A45: Anatomy | B45: Abdomen and Pelvis | C45: PM1292 | D45: Length of various structures in the human body | G45: =IF(COUNTIFS($A$2:A45,A45,$C$2:C45,C45)=1,1,0) -> 1 | H45: =IF(COUNTIFS($A$2:A45,A45,$B$2:B45,B45)=1,1,0) -> 0
A46: Anatomy | B46: Abdomen and Pelvis | C46: PM1265 | D46: Features of anal canal above and below pectinate line | G46: =IF(COUNTIFS($A$2:A46,A46,$C$2:C46,C46)=1,1,0) -> 1 | H46: =IF(COUNTIFS($A$2:A46,A46,$B$2:B46,B46)=1,1,0) -> 0
A47: Anatomy | B47: Abdomen and Pelvis | C47: PM1237 | D47: Sacral Plexus | G47: =IF(COUNTIFS($A$2:A47,A47,$C$2:C47,C47)=1,1,0) -> 1 | H47: =IF(COUNTIFS($A$2:A47,A47,$B$2:B47,B47)=1,1,0) -> 0
... A110: Anatomy | B110: Neuroanatomy | C110: PM2251 | D110: Neurons and fibers of the cerebellum | G110: =IF(COUNTIFS($A$2:A110,A110,$C$2:C110,C110)=1,1,0) -> 1 | H110: =IF(COUNTIFS($A$2:A110,A110,$B$2:B110,B110)=1,1,0) -> 0
A111: Anatomy | B111: Neuroanatomy | C111: PM2250 | D111: Layers of the cerebellar cortex | E111: Histology | G111: =IF(COUNTIFS($A$2:A111,A111,$C$2:C111,C111)=1,1,0) -> 0 | H111: =IF(COUNTIFS($A$2:A111,A111,$B$2:B111,B111)=1,1,0) -> 0
A112: Anatomy | B112: Neuroanatomy | C112: PM2248 | D112: Layers of Cerebral Cortex | E112: Histology | G112: =IF(COUNTIFS($A$2:A112,A112,$C$2:C112,C112)=1,1,0) -> 0 | H112: =IF(COUNTIFS($A$2:A112,A112,$B$2:B112,B112)=1,1,0) -> 0
A113: Anatomy | B113: Neuroanatomy | C113: PM2247 | D113: Internal capsule parts and fibers | G113: =IF(COUNTIFS($A$2:A113,A113,$C$2:C113,C113)=1,1,0) -> 1 | H113: =IF(COUNTIFS($A$2:A113,A113,$B$2:B113,B113)=1,1,0) -> 0
A114: Anatomy | B114: Neuroanatomy | C114: PM2246 | D114: Corpus Callosum | G114: =IF(COUNTIFS($A$2:A114,A114,$C$2:C114,C114)=1,1,0) -> 1 | H114: =IF(COUNTIFS($A$2:A114,A114,$B$2:B114,B114)=1,1,0) -> 0
A115: Anatomy | B115: Neuroanatomy | C115: PM2240 | D115: White matter tracts of the brain | G115: =IF(COUNTIFS($A$2:A115,A115,$C$2:C115,C115)=1,1,0) -> 1 | H115: =IF(COUNTIFS($A$2:A115,A115,$B$2:B115,B115)=1,1,0) -> 0
A116: Anatomy | B116: Neuroanatomy | C116: PM2239 | D116: Dural Venous Sinuses | G116: =IF(COUNTIFS($A$2:A116,A116,$C$2:C116,C116)=1,1,0) -> 1 | H116: =IF(COUNTIFS($A$2:A116,A116,$B$2:B116,B116)=1,1,0) -> 0
A117: Anatomy | B117: Neuroanatomy | C117: PM2233 | D117: Spinal Tract Decussations. | G117: =IF(COUNTIFS($A$2:A117,A117,$C$2:C117,C117)=1,1,0) -> 1 | H117: =IF(COUNTIFS($A$2:A117,A117,$B$2:B117,B117)=1,1,0) -> 0
A118: Anatomy | B118: Neuroanatomy | C118: PM2232 | D118: Descending tracts of spinal cord | G118: =IF(COUNTIFS($A$2:A118,A118,$C$2:C118,C118)=1,1,0) -> 1 | H118: =IF(COUNTIFS($A$2:A118,A118,$B$2:B118,B118)=1,1,0) -> 0
A119: Anatomy | B119: Neuroanatomy | C119: PM2231 | D119: Ascending tracts of spinal cord | G119: =IF(COUNTIFS($A$2:A119,A119,$C$2:C119,C119)=1,1,0) -> 1 | H119: =IF(COUNTIFS($A$2:A119,A119,$B$2:B119,B119)=1,1,0) -> 0
A120: Anatomy | B120: Neuroanatomy | C120: PM2141 | D120: Origins of cranial nerves at the base of the brain | G120: =IF(COUNTIFS($A$2:A120,A120,$C$2:C120,C120)=1,1,0) -> 1 | H120: =IF(COUNTIFS($A$2:A120,A120,$B$2:B120,B120)=1,1,0) -> 0
A121: Anatomy | B121: Neuroanatomy | C121: PM2140 | D121: Arrangement of cranial nerve nuclei in the brainstem | G121: =IF(COUNTIFS($A$2:A121,A121,$C$2:C121,C121)=1,1,0) -> 1 | H121: =IF(COUNTIFS($A$2:A121,A121,$B$2:B121,B121)=1,1,0) -> 0
A122: Anatomy | B122: Neuroanatomy | C122: PM2121 | D122: Functions of Main Hypothalamic Nuclei | G122: =IF(COUNTIFS($A$2:A122,A122,$C$2:C122,C122)=1,1,0) -> 1 | H122: =IF(COUNTIFS($A$2:A122,A122,$B$2:B122,B122)=1,1,0) -> 0
A123: Anatomy | B123: Neuroanatomy | C123: PM2063 | D123: Arteries supplying specific parts of the brain | G123: =IF(COUNTIFS($A$2:A123,A123,$C$2:C123,C123)=1,1,0) -> 1 | H123: =IF(COUNTIFS($A$2:A123,A123,$B$2:B123,B123)=1,1,0) -> 0
A124: Anatomy | B124: Neuroanatomy | C124: PM2017 | D124: Abnormal movements | G124: =IF(COUNTIFS($A$2:A124,A124,$C$2:C124,C124)=1,1,0) -> 1 | H124: =IF(COUNTIFS($A$2:A124,A124,$B$2:B124,B124)=1,1,0) -> 0
... A139: Anatomy | B139: Upper Limb | C139: PM2088 | D139: Brachial Plexus | G139: =IF(COUNTIFS($A$2:A139,A139,$C$2:C139,C139)=1,1,0) -> 1 | H139: =IF(COUNTIFS($A$2:A139,A139,$B$2:B139,B139)=1,1,0) -> 0
A140: Anatomy | B140: Upper Limb | C140: PM2053 | D140: Bursitis | E140: Lower Limb | G140: =IF(COUNTIFS($A$2:A140,A140,$C$2:C140,C140)=1,1,0) -> 1 | H140: =IF(COUNTIFS($A$2:A140,A140,$B$2:B140,B140)=1,1,0) -> 0
A141: Anatomy | B141: Upper Limb | C141: PM2002 | D141: Dermatome of upper limb | G141: =IF(COUNTIFS($A$2:A141,A141,$C$2:C141,C141)=1,1,0) -> 1 | H141: =IF(COUNTIFS($A$2:A141,A141,$B$2:B141,B141)=1,1,0) -> 0
A142: Anatomy | B142: Upper Limb | C142: PM1499 | D142: Compression neuropathies | E142: Lower Limb | G142: =IF(COUNTIFS($A$2:A142,A142,$C$2:C142,C142)=1,1,0) -> 1 | H142: =IF(COUNTIFS($A$2:A142,A142,$B$2:B142,B142)=1,1,0) -> 0
A143: Anatomy | B143: Upper Limb | C143: PM0772 | D143: Spaces of Hand | G143: =IF(COUNTIFS($A$2:A143,A143,$C$2:C143,C143)=1,1,0) -> 1 | H143: =IF(COUNTIFS($A$2:A143,A143,$B$2:B143,B143)=1,1,0) -> 0
A144: Anatomy | B144: Upper Limb | C144: PM0771 | D144: Structures Passing through the Extensor Retinaculum Compartments | G144: =IF(COUNTIFS($A$2:A144,A144,$C$2:C144,C144)=1,1,0) -> 1 | H144: =IF(COUNTIFS($A$2:A144,A144,$B$2:B144,B144)=1,1,0) -> 0
A145: Anatomy | B145: Upper Limb | C145: PM0757 | D145: Types of Joints in the Upper Limb | G145: =IF(COUNTIFS($A$2:A145,A145,$C$2:C145,C145)=1,1,0) -> 1 | H145: =IF(COUNTIFS($A$2:A145,A145,$B$2:B145,B145)=1,1,0) -> 0
A146: Anatomy | B146: Upper Limb | C146: PM0034 | D146: Dermatome and root value of the upper limb | G146: =IF(COUNTIFS($A$2:A146,A146,$C$2:C146,C146)=1,1,0) -> 1 | H146: =IF(COUNTIFS($A$2:A146,A146,$B$2:B146,B146)=1,1,0) -> 0
A147: Anatomy | B147: Lower Limb | C147: PM2401 | D147: Eponyms named after Friedrich Trendelenburg | G147: =IF(COUNTIFS($A$2:A147,A147,$C$2:C147,C147)=1,1,0) -> 1 | H147: =IF(COUNTIFS($A$2:A147,A147,$B$2:B147,B147)=1,1,0) -> 1
A148: Anatomy | B148: Lower Limb | C148: PM2396 | D148: Muscles causing the movements at Hip joint | G148: =IF(COUNTIFS($A$2:A148,A148,$C$2:C148,C148)=1,1,0) -> 1 | H148: =IF(COUNTIFS($A$2:A148,A148,$B$2:B148,B148)=1,1,0) -> 0
A149: Anatomy | B149: Lower Limb | C149: PM2395 | D149: Comparative features of the medial and lateral longitudinal arches of the foot. | G149: =IF(COUNTIFS($A$2:A149,A149,$C$2:C149,C149)=1,1,0) -> 1 | H149: =IF(COUNTIFS($A$2:A149,A149,$B$2:B149,B149)=1,1,0) -> 0
A150: Anatomy | B150: Lower Limb | C150: PM2354 | D150: Adductor Canal | G150: =IF(COUNTIFS($A$2:A150,A150,$C$2:C150,C150)=1,1,0) -> 1 | H150: =IF(COUNTIFS($A$2:A150,A150,$B$2:B150,B150)=1,1,0) -> 0
A151: Anatomy | B151: Lower Limb | C151: PM2284 | D151: Movements and muscles tested - lower limb | G151: =IF(COUNTIFS($A$2:A151,A151,$C$2:C151,C151)=1,1,0) -> 1 | H151: =IF(COUNTIFS($A$2:A151,A151,$B$2:B151,B151)=1,1,0) -> 0
A152: Anatomy | B152: Lower Limb | C152: PM2283 | D152: Various muscles of the leg and their innervation: | G152: =IF(COUNTIFS($A$2:A152,A152,$C$2:C152,C152)=1,1,0) -> 1 | H152: =IF(COUNTIFS($A$2:A152,A152,$B$2:B152,B152)=1,1,0) -> 0
A153: Anatomy | B153: Lower Limb | C153: PM2281 | D153: Sciatic nerve divisions and supply | E153: Abdomen and Pelvis | G153: =IF(COUNTIFS($A$2:A153,A153,$C$2:C153,C153)=1,1,0) -> 0 | H153: =IF(COUNTIFS($A$2:A153,A153,$B$2:B153,B153)=1,1,0) -> 0
A154: Anatomy | B154: Lower Limb | C154: PM2053 | D154: Bursitis | E154: Upper Limb | G154: =IF(COUNTIFS($A$2:A154,A154,$C$2:C154,C154)=1,1,0) -> 0 | H154: =IF(COUNTIFS($A$2:A154,A154,$B$2:B154,B154)=1,1,0) -> 0
A155: Anatomy | B155: Lower Limb | C155: PM1499 | D155: Compression neuropathies | E155: Upper Limb | G155: =IF(COUNTIFS($A$2:A155,A155,$C$2:C155,C155)=1,1,0) -> 0 | H155: =IF(COUNTIFS($A$2:A155,A155,$B$2:B155,B155)=1,1,0) -> 0
A156: Anatomy | B156: Lower Limb | C156: PM1242 | D156: Structures Passing Through the Sciatic Foramens | G156: =IF(COUNTIFS($A$2:A156,A156,$C$2:C156,C156)=1,1,0) -> 1 | H156: =IF(COUNTIFS($A$2:A156,A156,$B$2:B156,B156)=1,1,0) -> 0
A157: Anatomy | B157: Lower Limb | C157: PM1241 | D157: Femoral Triangle | G157: =IF(COUNTIFS($A$2:A157,A157,$C$2:C157,C157)=1,1,0) -> 1 | H157: =IF(COUNTIFS($A$2:A157,A157,$B$2:B157,B157)=1,1,0) -> 0
A158: Anatomy | B158: Lower Limb | C158: PM1236 | D158: Lumbar Plexus | G158: =IF(COUNTIFS($A$2:A158,A158,$C$2:C158,C158)=1,1,0) -> 1 | H158: =IF(COUNTIFS($A$2:A158,A158,$B$2:B158,B158)=1,1,0) -> 0
A159: Anatomy | B159: Lower Limb | C159: PM1050 | D159: Anatomy of Femoral Canal | G159: =IF(COUNTIFS($A$2:A159,A159,$C$2:C159,C159)=1,1,0) -> 1 | H159: =IF(COUNTIFS($A$2:A159,A159,$B$2:B159,B159)=1,1,0) -> 0
A160: Anatomy | B160: Lower Limb | C160: PM0127 | D160: Unhappy triad of knee joint | G160: =IF(COUNTIFS($A$2:A160,A160,$C$2:C160,C160)=1,1,0) -> 1 | H160: =IF(COUNTIFS($A$2:A160,A160,$B$2:B160,B160)=1,1,0) -> 0
A161: Anatomy | B161: Thorax | C161: PM2386 | D161: Divisions and contents of the mediastinum | G161: =IF(COUNTIFS($A$2:A161,A161,$C$2:C161,C161)=1,1,0) -> 1 | H161: =IF(COUNTIFS($A$2:A161,A161,$B$2:B161,B161)=1,1,0) -> 1
A162: Anatomy | B162: Thorax | C162: PM2243 | D162: Articulations of ribs | G162: =IF(COUNTIFS($A$2:A162,A162,$C$2:C162,C162)=1,1,0) -> 1 | H162: =IF(COUNTIFS($A$2:A162,A162,$B$2:B162,B162)=1,1,0) -> 0
A163: Anatomy | B163: Thorax | C163: PM2117 | D163: Angle of Louis | G163: =IF(COUNTIFS($A$2:A163,A163,$C$2:C163,C163)=1,1,0) -> 1 | H163: =IF(COUNTIFS($A$2:A163,A163,$B$2:B163,B163)=1,1,0) -> 0
A164: Anatomy | B164: Thorax | C164: PM1991 | D164: Diaphragmatic openings | G164: =IF(COUNTIFS($A$2:A164,A164,$C$2:C164,C164)=1,1,0) -> 1 | H164: =IF(COUNTIFS($A$2:A164,A164,$B$2:B164,B164)=1,1,0) -> 0
A165: Anatomy | B165: Thorax | C165: PM1782 | D165: Structures passing through heart sulci | G165: =IF(COUNTIFS($A$2:A165,A165,$C$2:C165,C165)=1,1,0) -> 1 | H165: =IF(COUNTIFS($A$2:A165,A165,$B$2:B165,B165)=1,1,0) -> 0
A166: Anatomy | B166: Thorax | C166: PM1291 | D166: Bronchopulmonary Segments | G166: =IF(COUNTIFS($A$2:A166,A166,$C$2:C166,C166)=1,1,0) -> 1 | H166: =IF(COUNTIFS($A$2:A166,A166,$B$2:B166,B166)=1,1,0) -> 0
A167: Anatomy | B167: Thorax | C167: PM1284 | D167: Surface marking for Lungs and Pleura | G167: =IF(COUNTIFS($A$2:A167,A167,$C$2:C167,C167)=1,1,0) -> 1 | H167: =IF(COUNTIFS($A$2:A167,A167,$B$2:B167,B167)=1,1,0) -> 0
... A241: Physiology | B241: Central Nervous System | C241: PM1323 | D241: Neurotransmitters and Hormones that influence Feeding and Satiety Centers in the Hypothalamus | G241: =IF(COUNTIFS($A$2:A241,A241,$C$2:C241,C241)=1,1,0) -> 1 | H241: =IF(COUNTIFS($A$2:A241,A241,$B$2:B241,B241)=1,1,0) -> 0
A242: Physiology | B242: Central Nervous System | C242: PM0998 | D242: Effects of Various Lesions and Brainstem Transections | E242: The Respiratory System | G242: =IF(COUNTIFS($A$2:A242,A242,$C$2:C242,C242)=1,1,0) -> 1 | H242: =IF(COUNTIFS($A$2:A242,A242,$B$2:B242,B242)=1,1,0) -> 0
A243: Physiology | B243: Central Nervous System | C243: PM0997 | D243: Respiratory Centres | E243: The Respiratory System | G243: =IF(COUNTIFS($A$2:A243,A243,$C$2:C243,C243)=1,1,0) -> 1 | H243: =IF(COUNTIFS($A$2:A243,A243,$B$2:B243,B243)=1,1,0) -> 0
A244: Physiology | B244: Central Nervous System | C244: PM0922 | D244: Functions of hypothalamus | G244: =IF(COUNTIFS($A$2:A244,A244,$C$2:C244,C244)=1,1,0) -> 1 | H244: =IF(COUNTIFS($A$2:A244,A244,$B$2:B244,B244)=1,1,0) -> 0
A245: Physiology | B245: Central Nervous System | C245: PM0921 | D245: Reward and punishment centers in brain | G245: =IF(COUNTIFS($A$2:A245,A245,$C$2:C245,C245)=1,1,0) -> 1 | H245: =IF(COUNTIFS($A$2:A245,A245,$B$2:B245,B245)=1,1,0) -> 0
A246: Physiology | B246: Central Nervous System | C246: PM0920 | D246: Components of limbic system | G246: =IF(COUNTIFS($A$2:A246,A246,$C$2:C246,C246)=1,1,0) -> 1 | H246: =IF(COUNTIFS($A$2:A246,A246,$B$2:B246,B246)=1,1,0) -> 0
A247: Physiology | B247: Central Nervous System | C247: PM0919 | D247: Divisions of thalamic nuclei | G247: =IF(COUNTIFS($A$2:A247,A247,$C$2:C247,C247)=1,1,0) -> 1 | H247: =IF(COUNTIFS($A$2:A247,A247,$B$2:B247,B247)=1,1,0) -> 0
A248: Physiology | B248: Central Nervous System | C248: PM0918 | D248: Divisions of thalamus | G248: =IF(COUNTIFS($A$2:A248,A248,$C$2:C248,C248)=1,1,0) -> 1 | H248: =IF(COUNTIFS($A$2:A248,A248,$B$2:B248,B248)=1,1,0) -> 0
A249: Physiology | B249: Central Nervous System | C249: PM0917 | D249: Functions of principal afferent systems to cerebellum | G249: =IF(COUNTIFS($A$2:A249,A249,$C$2:C249,C249)=1,1,0) -> 1 | H249: =IF(COUNTIFS($A$2:A249,A249,$B$2:B249,B249)=1,1,0) -> 0
A250: Physiology | B250: Central Nervous System | C250: PM0915 | D250: Functional divisions of the cerebellum | G250: =IF(COUNTIFS($A$2:A250,A250,$C$2:C250,C250)=1,1,0) -> 1 | H250: =IF(COUNTIFS($A$2:A250,A250,$B$2:B250,B250)=1,1,0) -> 0
A251: Physiology | B251: Central Nervous System | C251: PM0907 | D251: Forms of Memory | G251: =IF(COUNTIFS($A$2:A251,A251,$C$2:C251,C251)=1,1,0) -> 1 | H251: =IF(COUNTIFS($A$2:A251,A251,$B$2:B251,B251)=1,1,0) -> 0
A252: Physiology | B252: Central Nervous System | C252: PM0905 | D252: Difference between NREM and REM Sleep | G252: =IF(COUNTIFS($A$2:A252,A252,$C$2:C252,C252)=1,1,0) -> 1 | H252: =IF(COUNTIFS($A$2:A252,A252,$B$2:B252,B252)=1,1,0) -> 0
A253: Physiology | B253: Central Nervous System | C253: PM0904 | D253: Neurochemical changes in Sleep-Wake Cycle | G253: =IF(COUNTIFS($A$2:A253,A253,$C$2:C253,C253)=1,1,0) -> 1 | H253: =IF(COUNTIFS($A$2:A253,A253,$B$2:B253,B253)=1,1,0) -> 0
A254: Physiology | B254: Central Nervous System | C254: PM0903 | D254: Distribution of Sleep Stages in Young Adults | G254: =IF(COUNTIFS($A$2:A254,A254,$C$2:C254,C254)=1,1,0) -> 1 | H254: =IF(COUNTIFS($A$2:A254,A254,$B$2:B254,B254)=1,1,0) -> 0
A255: Physiology | B255: Central Nervous System | C255: PM0902 | D255: Stages of Arousal and Sleep | G255: =IF(COUNTIFS($A$2:A255,A255,$C$2:C255,C255)=1,1,0) -> 1 | H255: =IF(COUNTIFS($A$2:A255,A255,$B$2:B255,B255)=1,1,0) -> 0
... A285: Physiology | B285: The Respiratory System | C285: PM1001 | D285: Respiratory responses to exercise | G285: =IF(COUNTIFS($A$2:A285,A285,$C$2:C285,C285)=1,1,0) -> 1 | H285: =IF(COUNTIFS($A$2:A285,A285,$B$2:B285,B285)=1,1,0) -> 0
A286: Physiology | B286: The Respiratory System | C286: PM0998 | D286: Effects of Various Lesions and Brainstem Transections | E286: Central Nervous System | G286: =IF(COUNTIFS($A$2:A286,A286,$C$2:C286,C286)=1,1,0) -> 0 | H286: =IF(COUNTIFS($A$2:A286,A286,$B$2:B286,B286)=1,1,0) -> 0
A287: Physiology | B287: The Respiratory System | C287: PM0997 | D287: Respiratory Centres | E287: Central Nervous System | G287: =IF(COUNTIFS($A$2:A287,A287,$C$2:C287,C287)=1,1,0) -> 0 | H287: =IF(COUNTIFS($A$2:A287,A287,$B$2:B287,B287)=1,1,0) -> 0
A288: Physiology | B288: The Respiratory System | C288: PM0996 | D288: Factors affecting 2,3 -DPG | G288: =IF(COUNTIFS($A$2:A288,A288,$C$2:C288,C288)=1,1,0) -> 1 | H288: =IF(COUNTIFS($A$2:A288,A288,$B$2:B288,B288)=1,1,0) -> 0
A289: Physiology | B289: The Respiratory System | C289: PM0983 | D289: Structure of Airways | G289: =IF(COUNTIFS($A$2:A289,A289,$C$2:C289,C289)=1,1,0) -> 1 | H289: =IF(COUNTIFS($A$2:A289,A289,$B$2:B289,B289)=1,1,0) -> 0
...

Sheet Anatomy
A1: Subtopic | B1: Pearl ID | C1: Pearl | D1: Also listed under | E1: Note
A2: Embryology | B2: PM2509 | C2: Upper Limb Nerve Injuries
A3: Embryology | B3: PM2393 | C3: Derivatives of Mesoderm
A4: Embryology | B4: PM2351 | C4: Embryology of the ear
A5: Embryology | B5: PM2348 | C5: Homologous structures in male and female genitalia
A6: Embryology | B6: PM2236 | C6: Twinning
A7: Embryology | B7: PM2028 | C7: Concepts of Fetal Circulation
A8: Embryology | B8: PM1979 | C8: Derivatives of Mesonephric (Wolffian) duct and Paramesonephric (Mullerian) duct
A9: Embryology | B9: PM1974 | C9: Neural crest derivatives
A10: Embryology | B10: PM1888 | C10: Summary of ocular embryogenesis
A11: Embryology | B11: PM1239 | C11: Embryological derivatives of the eye
A12: Embryology | B12: PM1215 | C12: Locations of Congenital Heart Disease
A13: Embryology | B13: PM1065 | C13: Difference between gastroschisis and omphalocele
... A25: Embryology | B25: PM0177 | C25: Tissue Stem Cells and their Location
A26: Histology | B26: PM2250 | C26: Layers of the cerebellar cortex | D26: Neuroanatomy
A27: Histology | B27: PM2248 | C27: Layers of Cerebral Cortex | D27: Neuroanatomy
A28: Histology | B28: PM1880 | C28: Cells of the epidermis
A29: Histology | B29: PM1075 | C29: Various Types of Exocrine Glands with Examples
A30: Histology | B30: PM1071 | C30: Various Types of Epithelium, Their Location and Functions
A31: Histology | B31: PM0709 | C31: Comparison between Types of Sweat Glands
A32: Histology | B32: PM0706 | C32: Microanatomy of Muscle Fibres
A33: Abdomen and Pelvis | B33: PM2366 | C33: Perineal Body
A34: Abdomen and Pelvis | B34: PM2282 | C34: Gluteal Muscles
A35: Abdomen and Pelvis | B35: PM2281 | C35: Sciatic nerve divisions and supply | D35: Lower Limb
A36: Abdomen and Pelvis | B36: PM2280 | C36: Various muscles of the gluteal region and their innervation
A37: Abdomen and Pelvis | B37: PM2214 | C37: Lymphatic drainage of pelvic structures
A38: Abdomen and Pelvis | B38: PM2080 | C38: Calot's triangle and Hepatocystic triangle
A39: Abdomen and Pelvis | B39: PM2078 | C39: Common sites of porto-systemic anastomosis in portal hypertension
A40: Abdomen and Pelvis | B40: PM1851 | C40: Fallopian tube
A41: Abdomen and Pelvis | B41: PM1580 | C41: Characteristic differentiating features of the jejunum and ileum
A42: Abdomen and Pelvis | B42: PM1371 | C42: Passaro’s Triangle
A43: Abdomen and Pelvis | B43: PM1352 | C43: Nerve supply in the pelvis
A44: Abdomen and Pelvis | B44: PM1351 | C44: Contents of the Broad ligament
A45: Abdomen and Pelvis | B45: PM1292 | C45: Length of various structures in the human body
A46: Abdomen and Pelvis | B46: PM1265 | C46: Features of anal canal above and below pectinate line
A47: Abdomen and Pelvis | B47: PM1237 | C47: Sacral Plexus
... A110: Neuroanatomy | B110: PM2251 | C110: Neurons and fibers of the cerebellum
A111: Neuroanatomy | B111: PM2250 | C111: Layers of the cerebellar cortex | D111: Histology
A112: Neuroanatomy | B112: PM2248 | C112: Layers of Cerebral Cortex | D112: Histology
A113: Neuroanatomy | B113: PM2247 | C113: Internal capsule parts and fibers
A114: Neuroanatomy | B114: PM2246 | C114: Corpus Callosum
A115: Neuroanatomy | B115: PM2240 | C115: White matter tracts of the brain
A116: Neuroanatomy | B116: PM2239 | C116: Dural Venous Sinuses
A117: Neuroanatomy | B117: PM2233 | C117: Spinal Tract Decussations.
A118: Neuroanatomy | B118: PM2232 | C118: Descending tracts of spinal cord
A119: Neuroanatomy | B119: PM2231 | C119: Ascending tracts of spinal cord
A120: Neuroanatomy | B120: PM2141 | C120: Origins of cranial nerves at the base of the brain
A121: Neuroanatomy | B121: PM2140 | C121: Arrangement of cranial nerve nuclei in the brainstem
A122: Neuroanatomy | B122: PM2121 | C122: Functions of Main Hypothalamic Nuclei
A123: Neuroanatomy | B123: PM2063 | C123: Arteries supplying specific parts of the brain
A124: Neuroanatomy | B124: PM2017 | C124: Abnormal movements
... A139: Upper Limb | B139: PM2088 | C139: Brachial Plexus
A140: Upper Limb | B140: PM2053 | C140: Bursitis | D140: Lower Limb
A141: Upper Limb | B141: PM2002 | C141: Dermatome of upper limb
A142: Upper Limb | B142: PM1499 | C142: Compression neuropathies | D142: Lower Limb
A143: Upper Limb | B143: PM0772 | C143: Spaces of Hand
A144: Upper Limb | B144: PM0771 | C144: Structures Passing through the Extensor Retinaculum Compartments
A145: Upper Limb | B145: PM0757 | C145: Types of Joints in the Upper Limb
A146: Upper Limb | B146: PM0034 | C146: Dermatome and root value of the upper limb
A147: Lower Limb | B147: PM2401 | C147: Eponyms named after Friedrich Trendelenburg
A148: Lower Limb | B148: PM2396 | C148: Muscles causing the movements at Hip joint
A149: Lower Limb | B149: PM2395 | C149: Comparative features of the medial and lateral longitudinal arches of the foot.
A150: Lower Limb | B150: PM2354 | C150: Adductor Canal
A151: Lower Limb | B151: PM2284 | C151: Movements and muscles tested - lower limb
A152: Lower Limb | B152: PM2283 | C152: Various muscles of the leg and their innervation:
A153: Lower Limb | B153: PM2281 | C153: Sciatic nerve divisions and supply | D153: Abdomen and Pelvis
A154: Lower Limb | B154: PM2053 | C154: Bursitis | D154: Upper Limb
A155: Lower Limb | B155: PM1499 | C155: Compression neuropathies | D155: Upper Limb
A156: Lower Limb | B156: PM1242 | C156: Structures Passing Through the Sciatic Foramens
A157: Lower Limb | B157: PM1241 | C157: Femoral Triangle
A158: Lower Limb | B158: PM1236 | C158: Lumbar Plexus
A159: Lower Limb | B159: PM1050 | C159: Anatomy of Femoral Canal
A160: Lower Limb | B160: PM0127 | C160: Unhappy triad of knee joint
A161: Thorax | B161: PM2386 | C161: Divisions and contents of the mediastinum
A162: Thorax | B162: PM2243 | C162: Articulations of ribs
A163: Thorax | B163: PM2117 | C163: Angle of Louis
A164: Thorax | B164: PM1991 | C164: Diaphragmatic openings
A165: Thorax | B165: PM1782 | C165: Structures passing through heart sulci
A166: Thorax | B166: PM1291 | C166: Bronchopulmonary Segments
A167: Thorax | B167: PM1284 | C167: Surface marking for Lungs and Pleura
... A174: Back | B174: PM1160 | C174: Vertebral Spines as Landmarks for the Viscera

Sheet Physiology
A1: Subtopic | B1: Pearl ID | C1: Pearl | D1: Also listed under | E1: Note
A2: General Physiology | B2: PM2358 | C2: Na+ - K+ ATPase pump
A3: General Physiology | B3: PM2317 | C3: Membrane receptors and their mechanisms
A4: General Physiology | B4: PM1972 | C4: Resting membrane potential (RMP) in tissues
A5: General Physiology | B5: PM1957 | C5: Extracellular fluid vs Intracellular fluid
A6: General Physiology | B6: PM1906 | C6: Graded potential vs Action potential
A7: General Physiology | B7: PM1905 | C7: Absolute and relative refractory period
A8: General Physiology | B8: PM1895 | C8: Sensory Receptors
A9: General Physiology | B9: PM1497 | C9: Glucose Transporters
A10: General Physiology | B10: PM1340 | C10: Factors affecting K+ distribution between ECF and ICF concentration
A11: General Physiology | B11: PM0730 | C11: Transient Receptor Potential (TRP) Ion Channels/Receptors
A12: General Physiology | B12: PM0463 | C12: Distribution of body fluids
A13: General Physiology | B13: PM0462 | C13: Daily fluid intake and output
... A68: Central Nervous System | B68: PM1323 | C68: Neurotransmitters and Hormones that influence Feeding and Satiety Centers in the Hypothalamus
A69: Central Nervous System | B69: PM0998 | C69: Effects of Various Lesions and Brainstem Transections | D69: The Respiratory System
A70: Central Nervous System | B70: PM0997 | C70: Respiratory Centres | D70: The Respiratory System
A71: Central Nervous System | B71: PM0922 | C71: Functions of hypothalamus
A72: Central Nervous System | B72: PM0921 | C72: Reward and punishment centers in brain
A73: Central Nervous System | B73: PM0920 | C73: Components of limbic system
A74: Central Nervous System | B74: PM0919 | C74: Divisions of thalamic nuclei
A75: Central Nervous System | B75: PM0918 | C75: Divisions of thalamus
A76: Central Nervous System | B76: PM0917 | C76: Functions of principal afferent systems to cerebellum
A77: Central Nervous System | B77: PM0915 | C77: Functional divisions of the cerebellum
A78: Central Nervous System | B78: PM0907 | C78: Forms of Memory
A79: Central Nervous System | B79: PM0905 | C79: Difference between NREM and REM Sleep
A80: Central Nervous System | B80: PM0904 | C80: Neurochemical changes in Sleep-Wake Cycle
A81: Central Nervous System | B81: PM0903 | C81: Distribution of Sleep Stages in Young Adults
A82: Central Nervous System | B82: PM0902 | C82: Stages of Arousal and Sleep
... A112: The Respiratory System | B112: PM1001 | C112: Respiratory responses to exercise
A113: The Respiratory System | B113: PM0998 | C113: Effects of Various Lesions and Brainstem Transections | D113: Central Nervous System
A114: The Respiratory System | B114: PM0997 | C114: Respiratory Centres | D114: Central Nervous System
A115: The Respiratory System | B115: PM0996 | C115: Factors affecting 2,3 -DPG
A116: The Respiratory System | B116: PM0983 | C116: Structure of Airways
A117: The Respiratory System | B117: PM0113 | C117: Zones of Pulmonary Blood Flow
A118: The Respiratory System | B118: PM0105 | C118: Physiological significance of Hering-Breuer inflation and deflation reflex
A119: The Respiratory System | B119: PM0104 | C119: Respiratory responses mediated by airway and lung receptors
A120: The Respiratory System | B120: PM0103 | C120: Side effect of opioids on Respiration
A121: The Respiratory System | B121: PM0096 | C121: Oxygen myoglobin dissociation curve
A122: The Respiratory System | B122: PM0095 | C122: P50
A123: The Respiratory System | B123: PM0090 | C123: Hyaline membrane disease
A124: The Respiratory System | B124: PM0087 | C124: Lung Compliance
A125: The Respiratory System | B125: PM0084 | C125: Important Points about Bronchial Tree
A126: The Cardiovascular System | B126: PM2416 | C126: JVP waveform and the abnormalities
... A208: Special Senses | B208: PM0539 | C208: Sensory receptors in the inner ear
A209: Others | B209: PM2479 | C209: Physiologic effects of thyroid hormone | E209: Title cut off in the screenshot; full title supplied by the user

Sheet Biochemistry
A1: Subtopic | B1: Pearl ID | C1: Pearl | D1: Also listed under | E1: Note
A2: General Topics- Videos | B2: PM0909 | C2: Factors Affecting the Rate of Reaction
A3: Carbohydrates | B3: PM2311 | C3: Pyruvate metabolism
A4: Carbohydrates | B4: PM2309 | C4: Transport of ammonia in blood (Cahill and Cori cycle)
A5: Carbohydrates | B5: PM2194 | C5: Essential Pentosuria
A6: Carbohydrates | B6: PM2054 | C6: Irreversible enzymes in gluconeogenesis pathway
A7: Carbohydrates | B7: PM0982 | C7: Phases of HMP Shunt and the Enzymes Involved
A8: Carbohydrates | B8: PM0964 | C8: Glycogen Storage Diseases
A9: Carbohydrates | B9: PM0963 | C9: Glycogenolysis
A10: Carbohydrates | B10: PM0962 | C10: Steps in Glycogenesis & Respective Enzymes
A11: Carbohydrates | B11: PM0961 | C11: Structural Bond of Various Polysaccharides
A12: Carbohydrates | B12: PM0944 | C12: Test for Carbohydrates
A13: Carbohydrates | B13: PM0943 | C13: Method of Glucose Estimation
... A16: Carbohydrates | B16: PM0936 | C16: Aldoses and Ketoses
A17: Carbohydrates | B17: PM0856 | C17: Lysosomal storage diseases | D17: Lipids
A18: Carbohydrates | B18: PM0816 | C18: Diseases due to glycoprotein defect
A19: Carbohydrates | B19: PM0808 | C19: Some Important Methods Used to Study Glycoproteins
A20: Carbohydrates | B20: PM0807 | C20: Glycoprotein and their functions
A21: Carbohydrates | B21: PM0525 | C21: Reducing Equivalents and Their Uses | D21: Lipids
A22: Carbohydrates | B22: PM0091 | C22: Steps involved in TCA cycle
A23: Carbohydrates | B23: PM0081 | C23: Biologically important Glycosoaminoglycans(GAG's)
A24: Carbohydrates | B24: PM0080 | C24: Energy production in TCA Cycle | D24: Bioenergetics
A25: Carbohydrates | B25: PM0079 | C25: Inhibitors of metabolic pathways
A26: Carbohydrates | B26: PM0078 | C26: Electron transport chain: components and its inhibitors | D26: Bioenergetics
A27: Carbohydrates | B27: PM0030 | C27: Sites of various pathways in cell | D27: Amino acids and proteins; Lipids
A28: Carbohydrates | B28: PM0002 | C28: Glucose transporters and their locations
A29: Amino acids and proteins | B29: PM2322 | C29: Carcinoid syndrome
A30: Amino acids and proteins | B30: PM2310 | C30: Maple syrup urine disease(MSUD)
A31: Amino acids and proteins | B31: PM2307 | C31: Menkes disease | D31: Genetics
A32: Amino acids and proteins | B32: PM2306 | C32: Synthesis of collagen and its disorders
A33: Amino acids and proteins | B33: PM2305 | C33: Phenylketonuria
A34: Amino acids and proteins | B34: PM2304 | C34: Homocystinuria
A35: Amino acids and proteins | B35: PM2196 | C35: Amino Acid Derivatives
A36: Amino acids and proteins | B36: PM1791 | C36: Types of Chromatography
A37: Amino acids and proteins | B37: PM1402 | C37: Types of flavoprotein
A38: Amino acids and proteins | B38: PM1401 | C38: Structure of proteins
A39: Amino acids and proteins | B39: PM0627 | C39: Inborn Errors of Amino Acid Metabolism and Their Associated Urine Odor
A40: Amino acids and proteins | B40: PM0625 | C40: Amino acid Enzymatic Disorders and the Associated Enzymes
A41: Amino acids and proteins | B41: PM0590 | C41: Types of tyrosinemia with deficient enzymes
A42: Amino acids and proteins | B42: PM0579 | C42: Amino Acids and their Biological Amines
A43: Amino acids and proteins | B43: PM0576 | C43: Catabolism of Glycine
... A50: Amino acids and proteins | B50: PM0569 | C50: Amino Acid Classification Based on Metabolism (Glucogenic/Ketogenic ) and Nutritional requirement (Essential/Non essential)
A51: Amino acids and proteins | B51: PM0030 | C51: Sites of various pathways in cell | D51: Carbohydrates; Lipids
A52: Lipids | B52: PM2219 | C52: Cholesterol synthesis
A53: Lipids | B53: PM2169 | C53: Familial Dyslipidemias
A54: Lipids | B54: PM2109 | C54: Unsaturated Fatty acids
A55: Lipids | B55: PM1018 | C55: Hormone sensitive lipase Vs lipoprotein lipase
A56: Lipids | B56: PM0856 | C56: Lysosomal storage diseases | D56: Carbohydrates
A57: Lipids | B57: PM0768 | C57: Action of various prostaglandins on different organs:
A58: Lipids | B58: PM0767 | C58: Enzymes for COX pathway
A59: Lipids | B59: PM0765 | C59: Difference in COX-1 and COX-2
A60: Lipids | B60: PM0753 | C60: Examples of Sphingolipidoses (Lipids-Storage Disease)
A61: Lipids | B61: PM0750 | C61: Composition of Glycosphingolipids
A62: Lipids | B62: PM0749 | C62: Types of Sphingolipids
A63: Lipids | B63: PM0748 | C63: Classification of Lipids on the Basis of Base-promoted Hydrolysis
A64: Lipids | B64: PM0747 | C64: Pulmonary Surfactant Composition
A65: Lipids | B65: PM0746 | C65: Types of Phospholipids
A66: Lipids | B66: PM0745 | C66: Distribution of Various Apolipoproteins on Lipoproteins
A67: Lipids | B67: PM0742 | C67: Lipoprotein: Types, Sources and Action
A68: Lipids | B68: PM0741 | C68: Fatty Acid Elongation
... A80: Lipids | B80: PM0631 | C80: Classification of Lipids
A81: Lipids | B81: PM0525 | C81: Reducing Equivalents and Their Uses | D81: Carbohydrates
A82: Lipids | B82: PM0480 | C82: Fatty Acid Synthesis Pathway
A83: Lipids | B83: PM0030 | C83: Sites of various pathways in cell | D83: Carbohydrates; Amino acids and proteins
A84: Enzymes and Porphyrins | B84: PM2426 | C84: Enzyme classification
A85: Enzymes and Porphyrins | B85: PM2425 | C85: Metals as cofactors and prosthetic groups in enzymes
A86: Enzymes and Porphyrins | B86: PM2421 | C86: Heme containing proteins
A87: Enzymes and Porphyrins | B87: PM2312 | C87: Enzymes active in phosphorylated and dephosphorylated state
A88: Enzymes and Porphyrins | B88: PM1398 | C88: Drugs precipitating porphyria: "BOOST CHAP"
A89: Enzymes and Porphyrins | B89: PM0913 | C89: Some Examples of Suicidal Inhibitors
A90: Enzymes and Porphyrins | B90: PM0912 | C90: Difference between Competitive & Non-Competitive inhibitors
A91: Enzymes and Porphyrins | B91: PM0911 | C91: Difference between Reversible and Irreversible Inhibitors
A92: Enzymes and Porphyrins | B92: PM0855 | C92: Principal Serum Enzymes Used in Clinical Diagnosis
A93: Enzymes and Porphyrins | B93: PM0844 | C93: Types of porphyria
A94: Enzymes and Porphyrins | B94: PM0766 | C94: Site of synthesis of various Cox products
A95: Enzymes and Porphyrins | B95: PM0595 | C95: Human Porphyrias and Their Features
... A112: Genetics | B112: PM2327 | C112: Purine salvage deficiencies: Lesch-Nyhan syndrome and Adenosine deaminase deficiency(SCID)
A113: Genetics | B113: PM2307 | C113: Menkes disease | D113: Amino acids and proteins
A114: Genetics | B114: PM2151 | C114: Operon system
A115: Genetics | B115: PM1111 | C115: Structural Alterations of the β-Globin Gene
A116: Genetics | B116: PM1110 | C116: Localization of Human Genes
A117: Genetics | B117: PM1109 | C117: Some Enzymes Used in Recombinant DNA Research
A118: Genetics | B118: PM1108 | C118: Difference between Lac & tryptophan operon
A119: Genetics | B119: PM1107 | C119: Types of Genes
A120: Genetics | B120: PM1064 | C120: Human Diseases of DNA Damage Repair
A121: Genetics | B121: PM1063 | C121: DNA Repair Mechanisms
A122: Genetics | B122: PM1062 | C122: Types of Damage to DNA
A123: Genetics | B123: PM1061 | C123: Types of DNA polymerase
A124: Genetics | B124: PM1060 | C124: Enzymes Involved in DNA Replication
A125: Genetics | B125: PM1059 | C125: Role of Histones
... A135: Genetics | B135: PM0751 | C135: Niemann-Pick Disease Types and Symptoms
A136: Bioenergetics | B136: PM0080 | C136: Energy production in TCA Cycle | D136: Carbohydrates
A137: Bioenergetics | B137: PM0078 | C137: Electron transport chain: components and its inhibitors | D137: Carbohydrates
A138: Genetic Code | B138: PM2095 | C138: Start and stop codons
A139: Molecular Biology | B139: PM0414 | C139: Ribosomal Assembly (Prokaroytes)
A140: Metabolism of Xenobiotics | B140: PM2344 | C140: Types of Jaundice

Sheet Pathology
A1: Subtopic | B1: Pearl ID | C1: Pearl | D1: Also listed under | E1: Note
A2: General Pathology | B2: PM2412 | C2: Types of Hypersensitivity
A3: General Pathology | B3: PM2357 | C3: Types of calcifications
A4: General Pathology | B4: PM2356 | C4: Intracellular accumulations
A5: General Pathology | B5: PM2355 | C5: Types of granulomas
A6: General Pathology | B6: PM2353 | C6: Types of giant cells
A7: General Pathology | B7: PM2352 | C7: Chronic granulomatous disease
A8: General Pathology | B8: PM2265 | C8: Onion Skin Appearance in Pathology
A9: General Pathology | B9: PM2227 | C9: Necrosis vs Apoptosis
A10: General Pathology | B10: PM2206 | C10: Various stains and their applications in Pathology and Microbiology
A11: General Pathology | B11: PM2173 | C11: Pattern of nuclear body suggests the type of antibody present in patient’s serum.
A12: General Pathology | B12: PM2137 | C12: Transplant Rejection and Hypersensitivity
A13: General Pathology | B13: PM2112 | C13: Tumor suppressor genes
... A88: Hemolytic Anemias & RBC Disorders | B88: PM1468 | C88: WHO Polycythemia Vera Criteria
A89: Hemolytic Anemias & RBC Disorders | B89: PM1285 | C89: Morphological Classification of Anemias | D89: Hematology
A90: Hemolytic Anemias & RBC Disorders | B90: PM0027 | C90: Autoimmune Hemolytic Anemia
A91: Hematology | B91: PM2430 | C91: FAB classification of ALL
A92: Hematology | B92: PM2429 | C92: Causes of Thrombocytopenia
A93: Hematology | B93: PM2423 | C93: Burkitt's Lymphoma
A94: Hematology | B94: PM2420 | C94: Causes of Iron Deficiency Anemia
A95: Hematology | B95: PM2419 | C95: Factors affecting iron absorption
A96: Hematology | B96: PM2146 | C96: Differential Diagnosis of Microcytic Anaemia
A97: Hematology | B97: PM2064 | C97: Thalassemia syndromes
A98: Hematology | B98: PM1998 | C98: Important Translocations in AML
A99: Hematology | B99: PM1965 | C99: International Staging System (ISS) for multiple myeloma:
A100: Hematology | B100: PM1951 | C100: Platelet disorders
A101: Hematology | B101: PM1949 | C101: Differences between Bleeding Disorders and Coagulation disorders
... A117: Hematology | B117: PM1440 | C117: Causes of Megaloblastic Anemia
A118: Hematology | B118: PM1285 | C118: Morphological Classification of Anemias | D118: Hemolytic Anemias & RBC Disorders
A119: Hematology | B119: PM1273 | C119: Classification of acquired Immune Hemolytic Anemias
A120: Hematology | B120: PM1268 | C120: Features of Peripheral Blood Smear in Different Anemias
A121: Hematology | B121: PM1247 | C121: Classification of Hemolytic Anemias
A122: Hematology | B122: PM1244 | C122: WHO classification of Acute Myeloid Leukemia (AML)
A123: Hematology | B123: PM1235 | C123: Cytogenetic Translocation and Associated Oncogenes Often Seen in Lymphoid Malignancies
A124: Hematology | B124: PM1207 | C124: Prognostic Factors in Acute Myeloid Leukemia (AML)
A125: Hematology | B125: PM1193 | C125: Cytochemistry of Acute Leukemias
A126: Hematology | B126: PM1190 | C126: Immunophenotyping of Acute Lymphocytic Leukemia (ALL)
A127: Hematology | B127: PM1188 | C127: Panel of monoclonal antibodies for classification of leukemias
A128: Hematology | B128: PM1187 | C128: FAB classification
A129: Hematology | B129: PM1179 | C129: Morphological Characteristics of Blasts Cells in Acute Lymphoblastic Leukemia vs. Acute Myeloid Leukemia
A130: Hematology | B130: PM1178 | C130: Prognostic Factors in Acute Lymphoblastic Leukemia (ALL)
... A148: Systemic Pathology | B148: PM2493 | C148: Neurocutaneous syndomes
A149: Systemic Pathology | B149: PM2482 | C149: Histological Features of CNS Tumors | D149: Nervous System
A150: Systemic Pathology | B150: PM1570 | C150: Manifestations of systemic sclerosis
A151: Systemic Pathology | B151: PM1569 | C151: Characteristic Findings in Systemic Lupus Erythematosus (SLE)
A152: Systemic Pathology | B152: PM1316 | C152: Rhinosporidiosis
A153: Systemic Pathology | B153: PM0954 | C153: Important Vasculitis with Features
A154: Systemic Pathology | B154: PM0953 | C154: Primary Forms of Vasculitis with Sites of Involvement
A155: Systemic Pathology | B155: PM0952 | C155: Classification of vasculitis - Modified Chapel Hill classification
A156: Systemic Pathology | B156: PM0950 | C156: Classification of Vasculitis based on Pathogenesis
A157: Systemic Pathology | B157: PM0546 | C157: Classification of Gout
A158: Systemic Pathology | B158: PM0049 | C158: Radiosensitive and Radioresistant Tumors
A159: Cardiovascular System | B159: PM2026 | C159: Modified Duke's criteria for diagnosis of infective endocarditis
A160: Cardiovascular System | B160: PM1984 | C160: Vegetations in Various Types of Endocarditis
A161: Cardiovascular System | B161: PM1981 | C161: One-liners on Hypertrophic Cardiomyopathy (HCM)
... A249: Skin and Musculoskeletal system | B249: PM0185 | C249: Antibodies in Dermatomyositis
A250: Nervous System | B250: PM2482 | C250: Histological Features of CNS Tumors | D250: Systemic Pathology
A251: Nervous System | B251: PM2321 | C251: Classification and WHO Grading of Brain tumors
A252: Nervous System | B252: PM2319 | C252: Most commons of Brain tumours
A253: Nervous System | B253: PM2316 | C253: Synucleinopathies and tauopathies
A254: Nervous System | B254: PM2315 | C254: CNS infections and regions commonly affected
A255: Nervous System | B255: PM1746 | C255: Chromosomal abnormalities and syndromes associated with brain tumors
A256: Others | B256: PM2060 | C256: Paraneoplastic dermatoses
A257: Others | B257: PM1670 | C257: Differentiation of Mesothelioma from Adenocarcinoma
A258: Others | B258: PM0011 | C258: Types of Bone sequestra seen in chronic osteomyelitis

Sheet Pharmacology
A1: Subtopic | B1: Pearl ID | C1: Pearl | D1: Also listed under | E1: Note
A2: General Pharmacology | B2: PM2414 | C2: Drugs causing QT prolongation and torsades de pointes
A3: General Pharmacology | B3: PM2379 | C3: Drug regulatory schedules 1940: (2016 update)
A4: General Pharmacology | B4: PM2378 | C4: Zero order vs First order kinetics of drugs
A5: General Pharmacology | B5: PM2369 | C5: Drugs metabolised by glucuronidation
A6: General Pharmacology | B6: PM2368 | C6: Metabolism of drugs
A7: General Pharmacology | B7: PM2367 | C7: Dialyzable and non-dialyzable drugs
A8: General Pharmacology | B8: PM2365 | C8: Drugs which need Therapeutic Drug Monitoring (TDM)
A9: General Pharmacology | B9: PM2364 | C9: Drugs having high first pass metabolism
A10: General Pharmacology | B10: PM2363 | C10: Drugs showing increased absorption in presence of food
A11: General Pharmacology | B11: PM2022 | C11: Teratogenic drugs and the birth defects
A12: General Pharmacology | B12: PM1735 | C12: Difference between microsomal and non microsomal enzymes:
A13: General Pharmacology | B13: PM1734 | C13: Phases of drug metabolism
... A113: Endocrine System | B113: PM0679 | C113: Drug of choice for hyperthyroidism/thyrotoxicosis in pregnancy
A114: Endocrine System | B114: PM0553 | C114: PDE inhibitors | D114: Respiratory System
A115: Endocrine System | B115: PM0371 | C115: Mechanisms of Action of Hormones
A116: Endocrine System | B116: PM0370 | C116: Classification of Hormones According to their Chemical Structure
A117: Autacoids | B117: PM2335 | C117: Important drugs for rheumatoid arthritis
A118: Autacoids | B118: PM1929 | C118: Drugs precipitating Gout
A119: Autacoids | B119: PM0765 | C119: Difference in COX-1 and COX-2
A120: Autacoids | B120: PM0642 | C120: Acid resistant penicillins: mnemonic "VODKA"
A121: Autacoids | B121: PM0605 | C121: Factor Xa: IIa inhibition activity of antithrombin activators
A122: Autacoids | B122: PM0580 | C122: Triptans - 5HT 1B/1D agonists
A123: Autacoids | B123: PM0523 | C123: Some Important Points about Selective COX-2 Inhibitors
A124: Autacoids | B124: PM0522 | C124: Preferential COX-2 inhibitors: mnemonic "NAMED"
A125: Autacoids | B125: PM0521 | C125: Prostaglandins effect on platelet action
A126: Hematology | B126: PM2398 | C126: Classification of anti-platelet drugs
... A131: Hematology | B131: PM0603 | C131: Plasminogen activators (classification of fibrinolytics)
A132: Respiratory System | B132: PM0553 | C132: PDE inhibitors | D132: Endocrine System
A133: Gastrointestinal Drugs | B133: PM2457 | C133: Drugs used in irritable bowel syndrome (IBS)
A134: Anti-Neoplastic Agents | B134: PM1565 | C134: Uses of methotrexate (mnemonic: CANCER)
A135: Anti-Neoplastic Agents | B135: PM1517 | C135: Unique adverse effect profile of Zidovudine
A136: Anti-Neoplastic Agents | B136: PM1353 | C136: Classification of antineoplastic drugs
A137: Anti-Neoplastic Agents | B137: PM1082 | C137: Monoclonal antibodies nomenclature
A138: Anti-Neoplastic Agents | B138: PM1081 | C138: Indications for Imatinib
A139: Anti-Neoplastic Agents | B139: PM0925 | C139: Microtubule stabilising vs polymerisation inhibiting agents
A140: Anti-Neoplastic Agents | B140: PM0914 | C140: Cell cycle specific and non-specific cytotoxic agents
A141: Anti-Neoplastic Agents | B141: PM0910 | C141: Topoisomerase Inhibitors
A142: Newer Drugs | B142: PM2405 | C142: FDA approved drugs in 2019
A143: Newer Drugs | B143: PM1787 | C143: FDA approved drugs in 2017
A144: Newer Drugs | B144: PM0296 | C144: Treatment Ladder for Psoriasis

Sheet Forensic Medicine
A1: Subtopic | B1: Pearl ID | C1: Pearl | D1: Also listed under | E1: Note
A2: Identification | B2: PM0060 | C2: Estimation of stature using skeletal remains
A3: Identification | B3: PM0059 | C3: Medico-legal importance of age
A4: Identification | B4: PM0058 | C4: Ossification centres appearing before birth
A5: Identification | B5: PM0057 | C5: Appearance of ossification centres of carpal bones
A6: Identification | B6: PM0056 | C6: Fusion of skull sutures and closure of fontanelles
A7: Identification | B7: PM0055 | C7: Permanent dentition
A8: Identification | B8: PM0054 | C8: Temporary dentition
A9: Identification | B9: PM0053 | C9: Indices for determination of race and sex of an individual
A10: Identification | B10: PM0050 | C10: Cephalic index
A11: Medical Jurisprudence | B11: PM2391 | C11: Contributory negligence
A12: Medical Jurisprudence | B12: PM2131 | C12: Medical Termination of Pregnancy Act - MTP Act 1971
A13: Medical Jurisprudence | B13: PM2059 | C13: BNS section 22, M'Naghten's rule
... A94: Others | B94: PM0861 | C94: Post-mortem Staining in Poisonings

Sheet Community Medicine
A1: Subtopic | B1: Pearl ID | C1: Pearl | D1: Also listed under | E1: Note
A2: Preventive medicine - Marrow Edition 3 (2019) | B2: PM2211 | C2: Vaccines and their Strains
A3: Concepts of Health and Disease | B3: PM2224 | C3: Health Data
A4: Concepts of Health and Disease | B4: PM2044 | C4: Crude death rate
A5: Concepts of Health and Disease | B5: PM1700 | C5: Neonatal Mortality Rate
A6: Concepts of Health and Disease | B6: PM1699 | C6: Perinatal Mortality Rate
A7: Concepts of Health and Disease | B7: PM1698 | C7: Maternal Mortality Ratio
A8: Concepts of Health and Disease | B8: PM0138 | C8: Socio-Economic Indicators of Health
A9: Concepts of Health and Disease | B9: PM0137 | C9: Disability Adjusted Life Year (DALY)
A10: Concepts of Health and Disease | B10: PM0136 | C10: QALY vs. DALY
A11: Concepts of Health and Disease | B11: PM0134 | C11: HDI vs. PQLI
A12: Epidemiology | B12: PM1691 | C12: National Immunization Schedule (India)
A13: Epidemiology | B13: PM0814 | C13: Methods of Sterilization and Disinfection
... A62: Epidemiology of Communicable Diseases | B62: PM1775 | C62: Recommendations - WHO Guidelines for preventive chemotherapy to control soil-transmitted helminth infections in at-risk population groups
A63: Epidemiology of Communicable Diseases | B63: PM1731 | C63: Arthropod-borne diseases | D63: Environment and Health
A64: Epidemiology of Communicable Diseases | B64: PM1726 | C64: Flea Indices
A65: Epidemiology of Communicable Diseases | B65: PM1725 | C65: Rabies vaccines and immunoglobulins schedules
A66: Epidemiology of Communicable Diseases | B66: PM1724 | C66: Classification of Zoonoses
A67: Epidemiology of Communicable Diseases | B67: PM1720 | C67: ATT Regimen for TB Patients
A68: Epidemiology of Communicable Diseases | B68: PM1719 | C68: Classification of TB Patients Based on History of Treatment
A69: Epidemiology of Communicable Diseases | B69: PM1718 | C69: Diagnostic algorithm for Pulmonary TB — National Tuberculosis Elimination Programme (NTEP) 2020 Guidelines
A70: Epidemiology of Communicable Diseases | B70: PM1713 | C70: Ridley's logarithmic scale in determining Bacterial Index
A71: Epidemiology of Communicable Diseases | B71: PM1710 | C71: Important sexually transmitted pathogens and the diseases caused by them
A72: Epidemiology of Communicable Diseases | B72: PM1696 | C72: Treatment of Malaria
A73: Epidemiology of Communicable Diseases | B73: PM0594 | C73: 2021 NACO Guidelines on Post-exposure Prophylaxis (PEP) for HIV
A74: Epidemiology of Communicable Diseases | B74: PM0495 | C74: Biological Transmission in Vector-Borne Diseases
A75: Epidemiology of Communicable Diseases | B75: PM0491 | C75: Modes of Transmission of Communicable Diseases
... A131: Environment and Health | B131: PM2390 | C131: Comparison between mosquito-borne and transfusion-transmitted malaria.
A132: Environment and Health | B132: PM1731 | C132: Arthropod-borne diseases | D132: Epidemiology of Communicable Diseases
A133: Environment and Health | B133: PM1686 | C133: Insecticides
A134: Environment and Health | B134: PM1684 | C134: Ticks
A135: Environment and Health | B135: PM1683 | C135: Rat Fleas
A136: Environment and Health | B136: PM1681 | C136: Lice
A137: Environment and Health | B137: PM1676 | C137: Sandfly
A138: Environment and Health | B138: PM1669 | C138: Mosquito Control Measures
A139: Environment and Health | B139: PM1668 | C139: The Mosquito
A140: Environment and Health | B140: PM1666 | C140: Oxidation Ponds
A141: Environment and Health | B141: PM1664 | C141: Modern Sewage Treatment
A142: Environment and Health | B142: PM1662 | C142: Strength of Sewage
A143: Environment and Health | B143: PM1661 | C143: Septic Tank
A144: Environment and Health | B144: PM1660 | C144: RCA Latrines
... A184: Communication for Health Education | B184: PM0173 | C184: Principles of Health Education
A185: Communication for Health Education | B185: PM0167 | C185: Evaluation of a Health Program | D185: Healthcare of the Community
A186: Communication for Health Education | B186: PM0164 | C186: Network Analysis in Health Management
A187: Healthcare of the Community | B187: PM0845 | C187: The Family as a Social Organization
A188: Healthcare of the Community | B188: PM0172 | C188: Health Education vs. Propaganda
A189: Healthcare of the Community | B189: PM0167 | C189: Evaluation of a Health Program | D189: Communication for Health Education
A190: Healthcare of the Community | B190: PM0160 | C190: Responsibilities of Health Workers
A191: Healthcare of the Community | B191: PM0159 | C191: Community Health Centre Human Resources
A192: Healthcare of the Community | B192: PM0158 | C192: Primary Health Centres- PHC
A193: Healthcare of the Community | B193: PM0157 | C193: Sub-centre vs. PHC vs. CHC
A194: Healthcare of the Community | B194: PM0156 | C194: ASHA
A195: Healthcare of the Community | B195: PM0154 | C195: Suggested Norms for Health Workforce
A196: Healthcare of the Community | B196: PM0153 | C196: Elements and Principles of Primary Health Care
A197: International Health | B197: PM2208 | C197: Organizations and their Headquarters
A198: International Health | B198: PM1820 | C198: Health-related International Declarations:
A199: International Health | B199: PM0151 | C199: Diseases of International Significance
A200: International Health | B200: PM0148 | C200: GOBI-FFF Strategy
A201: International Health | B201: PM0147 | C201: World Health Organization
... A203: Biostatistics | B203: PM2138 | C203: Scales of data measurement
A204: Biostatistics | B204: PM1150 | C204: Box and Whisker Plot | D204: Minor topics
A205: Biostatistics | B205: PM1149 | C205: Forest Plot
A206: Biostatistics | B206: PM1148 | C206: Funnel Plots
A207: Biostatistics | B207: PM1147 | C207: Stem-and-Leaf Displays
A208: Biostatistics | B208: PM1146 | C208: Sampling
A209: Biostatistics | B209: PM1142 | C209: Regression
A210: Biostatistics | B210: PM1139 | C210: Correlation
A211: Biostatistics | B211: PM1104 | C211: Tests of Significance
A212: Biostatistics | B212: PM1103 | C212: Degrees of Freedom
A213: Biostatistics | B213: PM1098 | C213: Concepts in Hypothesis Testing
A214: Biostatistics | B214: PM1090 | C214: Confidence Limits and Interval
A215: Biostatistics | B215: PM1089 | C215: The Standard Error and Related Aspects
A216: Biostatistics | B216: PM1088 | C216: Coefficient of Variation
... A232: Minor topics | B232: PM1688 | C232: Pesticide Toxicity Labels
A233: Minor topics | B233: PM1150 | C233: Box and Whisker Plot | D233: Biostatistics
A234: Others | B234: PM2503 | C234: Rabies vaccines and immunoglobulins schedules
A235: Others | B235: PM2502 | C235: GOBI-FFF Strategy
A236: Others | B236: PM2442 | C236: WHO 2018 guidelines for post exposure prophylaxis regimen in HIV
A237: Others | B237: PM1144 | C237: Survival Analysis | E237: Title cut off in the screenshot; full title supplied by the user

Sheet ENT
A1: Subtopic | B1: Pearl ID | C1: Pearl | D1: Also listed under | E1: Note
A2: Ear | B2: PM2512 | C2: Stapedotomy special considerations and complications
A3: Ear | B3: PM2351 | C3: Embryology of the ear
A4: Ear | B4: PM2222 | C4: Myringotomy
A5: Ear | B5: PM2205 | C5: Eagle syndrome
A6: Ear | B6: PM1819 | C6: Auditory Brainstem Implant
A7: Ear | B7: PM1818 | C7: BAHA (Bone Anchored Hearing Aid)
A8: Ear | B8: PM1817 | C8: Cochlear implant
A9: Ear | B9: PM1807 | C9: Inner Ear Abnormalities
A10: Ear | B10: PM1800 | C10: Tuning fork tests
A11: Ear | B11: PM1755 | C11: BERA (Brainstem Evoked Response Audiometry) or ABR (Auditory Brainstem Response)
A12: Ear | B12: PM1754 | C12: OAEs - Otoacoustic emissions
A13: Ear | B13: PM1753 | C13: Speech audiometry
... A76: Pharynx | B76: PM1294 | C76: Parts of Pharynx
A77: Pharynx | B77: PM1097 | C77: Lymph Node Levels in the Neck | D77: Throat
A78: Larynx | B78: PM2513 | C78: TNM classification of glottic carcinoma
A79: Larynx | B79: PM1978 | C79: Muscles of larynx
A80: Larynx | B80: PM1801 | C80: Child vs Adult airway
A81: Larynx | B81: PM1096 | C81: Sites and subsites of the larynx (AJCC Classification)
A82: Larynx | B82: PM1094 | C82: Various Vocal Cord Palsies
A83: Larynx | B83: PM1093 | C83: Positions of the Vocal Cord
A84: Larynx | B84: PM1091 | C84: Nerves of Larynx
A85: Larynx | B85: PM0931 | C85: Differences between adult and infant Larynx
A86: Larynx | B86: PM0930 | C86: Development of Larynx
A87: Larynx | B87: PM0927 | C87: Cartilages of Larynx
A88: Larynx | B88: PM0403 | C88: Precautions during laser airway surgery
A89: Instruments | B89: PM1298 | C89: Laser Application in ENT
A90: Throat | B90: PM2157 | C90: Types of Tracheostomy
A91: Throat | B91: PM1097 | C91: Lymph Node Levels in the Neck | D91: Pharynx

Sheet Ophthalmology
A1: Subtopic | B1: Pearl ID | C1: Pearl | D1: Also listed under | E1: Note
A2: Basics of Ophthalmology | B2: PM2228 | C2: Superior orbital fissure
A3: Basics of Ophthalmology | B3: PM1888 | C3: Summary of ocular embryogenesis
A4: Basics of Ophthalmology | B4: PM1887 | C4: Visual development
A5: Basics of Ophthalmology | B5: PM1240 | C5: Extraocular Muscles and Their Actions
A6: Basics of Ophthalmology | B6: PM1239 | C6: Embryological derivatives of the eye
A7: Basics of Ophthalmology | B7: PM1084 | C7: Sympathetic and parasympathetic nerve supply to iris muscles
A8: Basics of Ophthalmology | B8: PM1014 | C8: Grades of binocular vision
A9: Basics of Ophthalmology | B9: PM1013 | C9: Laws governing ocular movements
A10: Basics of Ophthalmology | B10: PM0843 | C10: Axes of the Eye
A11: Basics of Ophthalmology | B11: PM0833 | C11: Differences between Rods and Cones
A12: Basics of Ophthalmology | B12: PM0800 | C12: Layers of the Tear Film | D12: Conjunctiva
A13: Basics of Ophthalmology | B13: PM0790 | C13: Causes of small and dilated pupils
A14: Basics of Ophthalmology | B14: PM0789 | C14: Order of neurons in the visual pathway
A15: Basics of Ophthalmology | B15: PM0406 | C15: Oculocardiac Reflex
A16: Errors in Optics | B16: PM0723 | C16: Surgical treatment of hypermetropia | D16: Cornea
A17: Errors in Optics | B17: PM0722 | C17: Grading of Hypermetropia
A18: Errors in Optics | B18: PM0721 | C18: Surgical correction of Myopia | D18: Cornea
A19: Errors in Optics | B19: PM0717 | C19: Grading of Myopia
A20: Errors in Optics | B20: PM0716 | C20: Causes of Myopia
A21: Errors in Optics | B21: PM0345 | C21: Types of contact lens (based on the material)
A22: Conjunctiva | B22: PM0801 | C22: Tear film tests used for the diagnosis of dry eye
A23: Conjunctiva | B23: PM0800 | C23: Layers of the Tear Film | D23: Basics of Ophthalmology
A24: Conjunctiva | B24: PM0799 | C24: Surgical treatment of different types of ptosis
A25: Conjunctiva | B25: PM0798 | C25: Surgical Modalities Used in Correcting Ectropion
A26: Conjunctiva | B26: PM0075 | C26: Trachoma Staging
A27: Cornea | B27: PM1919 | C27: Stromal Dystrophies and Staining
A28: Cornea | B28: PM1918 | C28: Causes of congenital opacities of the cornea
A29: Cornea | B29: PM1908 | C29: Important investigations related to the cornea
A30: Cornea | B30: PM1907 | C30: Clinical differential diagnosis of corneal ulcer
A31: Cornea | B31: PM1723 | C31: Different types of keratic precipitates (KPs) | D31: Specific Disorders of the Eye
A32: Cornea | B32: PM0783 | C32: Vogt's striae
A33: Cornea | B33: PM0755 | C33: Corneal Preservation
A34: Cornea | B34: PM0754 | C34: Corneal Opacities
A35: Cornea | B35: PM0723 | C35: Surgical treatment of hypermetropia | D35: Errors in Optics
A36: Cornea | B36: PM0721 | C36: Surgical correction of Myopia | D36: Errors in Optics
A37: Cornea | B37: PM0711 | C37: Types of Corneal Dystrophies
A38: Cornea | B38: PM0710 | C38: Ocular lesions of Herpes Simplex
A39: Retina and Vitreous | B39: PM2487 | C39: Early treatment diabetic retinopathy study (ETDRS) classification
A40: Retina and Vitreous | B40: PM2486 | C40: Hypertensive retinopathy
A41: Retina and Vitreous | B41: PM1475 | C41: Causes of loss of vision
A42: Retina and Vitreous | B42: PM1459 | C42: Reese Ellsworth classification for retinoblastoma
A43: Retina and Vitreous | B43: PM0795 | C43: Classification of optic atrophy
A44: Retina and Vitreous | B44: PM0792 | C44: Foster-Kennedy Syndrome
A45: Retina and Vitreous | B45: PM0365 | C45: Layers of Retina
A46: Retina and Vitreous | B46: PM0029 | C46: Important causes of cherry-red spots
A47: Glaucoma | B47: PM2204 | C47: Fincham’s Test
A48: Glaucoma | B48: PM1170 | C48: Important adverse effects of anti-glaucoma drugs
... A53: Specific Disorders of the Eye | B53: PM1950 | C53: Lesions in the optic pathway
A54: Specific Disorders of the Eye | B54: PM1723 | C54: Different types of keratic precipitates (KPs) | D54: Cornea
A55: Specific Disorders of the Eye | B55: PM1722 | C55: Congenital anomailes of the uveal tract
A56: Specific Disorders of the Eye | B56: PM0875 | C56: Maturation of Cortical Cataract | D56: Videos
A57: Specific Disorders of the Eye | B57: PM0874 | C57: Types of Congenital Cataract | D57: Videos
A58: Specific Disorders of the Eye | B58: PM0407 | C58: Complications and contraindications of retrobulbar block
A59: Practical Ophthalmology | B59: PM1898 | C59: Lasers in Ophthalmology
A60: Practical Ophthalmology | B60: PM1479 | C60: Difference between direct and indirect ophthalmoscopy
A61: Practical Ophthalmology | B61: PM1016 | C61: Cover tests in ophthalmology
A62: Practical Ophthalmology | B62: PM1015 | C62: Classification of Strabismus
A63: Systemic Ophthalmology | B63: PM1781 | C63: Signs in Grave’s ophthalmopathy
A64: Systemic Ophthalmology | B64: PM1728 | C64: Uveitis Associated with HLA B-27-associated Arthritis
A65: Systemic Ophthalmology | B65: PM1469 | C65: Ocular manifestation in infections
A66: Systemic Ophthalmology | B66: PM0897 | C66: Diseases and Associated Cataracts - Images
A67: Systemic Ophthalmology | B67: PM0879 | C67: Diseases and Their Associated Cataracts
A68: Community Ophthalmology | B68: PM1899 | C68: WHO classification of trachoma (FISTO)
A69: Community Ophthalmology | B69: PM1463 | C69: WHO grading of Vitamin A deficiency
... A73: Videos | B73: PM0878 | C73: Important symptoms and their occurrence in cataract
A74: Videos | B74: PM0875 | C74: Maturation of Cortical Cataract | D74: Specific Disorders of the Eye
A75: Videos | B75: PM0874 | C75: Types of Congenital Cataract | D75: Specific Disorders of the Eye
A76: Videos | B76: PM0797 | C76: Surgical Modalities Used in Correcting Entropion
A77: Others | B77: PM2451 | C77: Clinical findings in keratoconus

Sheet Medicine
A1: Subtopic | B1: Pearl ID | C1: Pearl | D1: Also listed under | E1: Note
A2: General | B2: PM2180 | C2: Hypervitaminosis A
A3: General | B3: PM2065 | C3: Body mass index
A4: General | B4: PM2055 | C4: Inheritance pattern of important diseases
A5: General | B5: PM2040 | C5: Conditions commonly associated with Klippel-Feil syndrome
A6: General | B6: PM1338 | C6: Principal buffers in the body
A7: General | B7: PM1233 | C7: Indications of Plasma exchange Therapy
A8: General | B8: PM0276 | C8: Pathological Conditions and Associated Neoplasms
A9: General | B9: PM0272 | C9: Paraneoplastic Syndromes and Underlying Cancers
A10: General | B10: PM0188 | C10: Adult cardiac arrest algorithm (Updated as per 2025 guidelines)
A11: General | B11: PM0180 | C11: Nail findings and associated systemic conditions
A12: General | B12: PM0133 | C12: Important dates and events
A13: Endocrine System | B13: PM2410 | C13: Classification of Anti- Thyroid Drugs
... A136: Respiratory System | B136: PM2190 | C136: Empirical Antibiotic Treatment of Community-Acquired Pneumonia (CAP)
A137: Respiratory System | B137: PM1977 | C137: Causes of CorPulmonale | D137: Cardiovascular System
A138: Respiratory System | B138: PM1879 | C138: Types of pleural effusion
A139: Respiratory System | B139: PM1863 | C139: Types of Respiratory Failure
A140: Respiratory System | B140: PM1845 | C140: Incidence of lung cancer according to histology
A141: Respiratory System | B141: PM1843 | C141: Lobes involved in various lung diseases
A142: Respiratory System | B142: PM1840 | C142: Extrinsic vs Intrinsic asthma
A143: Respiratory System | B143: PM1821 | C143: Evaluation of solitary pulmonary nodule
A144: Respiratory System | B144: PM1718 | C144: Diagnostic algorithm for Pulmonary TB — National Tuberculosis Elimination Programme (NTEP) 2020 Guidelines | D144: Infectious Diseases
A145: Respiratory System | B145: PM1555 | C145: Disorders Caused by Immediate Hypersensitivity
A146: Respiratory System | B146: PM1172 | C146: PFT for obstructive vs restrictive diseases
A147: Respiratory System | B147: PM1171 | C147: CURB-65 Criteria
A148: Respiratory System | B148: PM1165 | C148: Types of Bronchiectasis
A149: Respiratory System | B149: PM1012 | C149: Pulmonary surfactant
A150: Respiratory System | B150: PM1010 | C150: Lung volumes and capacities
A151: Respiratory System | B151: PM1009 | C151: Acclimatization to high altitude
A152: Respiratory System | B152: PM1008 | C152: Characteristics of different types of Hypoxia
A153: Respiratory System | B153: PM0996 | C153: Factors affecting 2,3 -DPG
A154: Respiratory System | B154: PM0584 | C154: Chest X Ray signs in pulmonary embolism
A155: Respiratory System | B155: PM0581 | C155: Causes of predominantly unilateral pleural effusion
A156: Respiratory System | B156: PM0150 | C156: Typical Pneumonia v/s Atypical Pneumonia
... A188: Cardiovascular System | B188: PM1981 | C188: One-liners on Hypertrophic Cardiomyopathy (HCM)
A189: Cardiovascular System | B189: PM1977 | C189: Causes of CorPulmonale | D189: Respiratory System
A190: Cardiovascular System | B190: PM1846 | C190: The causes of holosystolic murmur are:
A191: Cardiovascular System | B191: PM1834 | C191: Cardiac conditions requiring antibiotic prophylaxis for infective endocarditis
A192: Cardiovascular System | B192: PM1738 | C192: Revised 2024 ESC Guidelines on Hypertension
A193: Cardiovascular System | B193: PM1679 | C193: CHADS2 VASc Score (Risk of stroke in AF)
A194: Cardiovascular System | B194: PM1655 | C194: Prophylaxis for DVT
A195: Cardiovascular System | B195: PM1567 | C195: Anti-anginal drugs
A196: Cardiovascular System | B196: PM1227 | C196: Management of Hypertensive Emergency | D196: Emergency medicine and critical care
A197: Cardiovascular System | B197: PM1226 | C197: Target BP in hypertensive patients- European Society of Cardiology guidelines 2024
A198: Cardiovascular System | B198: PM1224 | C198: Parenteral drugs used in hypertensive emergencies | D198: Emergency medicine and critical care
A199: Cardiovascular System | B199: PM1223 | C199: European society of cardiology guidelines for treatment of hypertension
A200: Cardiovascular System | B200: PM1222 | C200: American Heart Association (AHA) 2019 guidelines for hypertension management
A201: Cardiovascular System | B201: PM1221 | C201: Causes of Secondary Hypertension
A202: Cardiovascular System | B202: PM1219 | C202: Classification of Hypertension
A203: Cardiovascular System | B203: PM1218 | C203: Classification of blood pressure for adults - European Society of Cardiology guidelines - 2018
A204: Cardiovascular System | B204: PM1214 | C204: Classification of Congenital Heart Disease in Adults
A205: Cardiovascular System | B205: PM1212 | C205: Localisation of MI based on ST elevations in different leads
A206: Cardiovascular System | B206: PM1211 | C206: ECG Leads
A207: Cardiovascular System | B207: PM1209 | C207: Drugs used in Pulmonary Arterial Hypertension (PAH)
A208: Cardiovascular System | B208: PM1208 | C208: Classification of Pulmonary Hypertension & its Causes
A209: Cardiovascular System | B209: PM1205 | C209: Indication for Pacemaker in AV Conduction Defects
A210: Cardiovascular System | B210: PM1204 | C210: Types of Heart block
... A231: Cardiovascular System | B231: PM0646 | C231: Definitions of Heart Failure According to EF (ESC HF guidelines 2016)
A232: Cardiovascular System | B232: PM0610 | C232: Contraindications for thrombolytic therapy | D232: Nervous System
A233: Cardiovascular System | B233: PM0607 | C233: Signs in Pericardial Effusion
A234: Cardiovascular System | B234: PM0603 | C234: Plasminogen activators (classification of fibrinolytics) | D234: Nervous System
A235: Cardiovascular System | B235: PM0598 | C235: American Heart Association (AHA) recommendation for duration of secondary prophylaxis of rheumatic fever
A236: Cardiovascular System | B236: PM0564 | C236: Causes of Pulsus Paradoxus
A237: Cardiovascular System | B237: PM0555 | C237: Vascular diseases — Gender differences
A238: Cardiovascular System | B238: PM0545 | C238: Microbiology of Infective Endocarditis
A239: Cardiovascular System | B239: PM0544 | C239: Source of microorganisms causing infective endocarditis
A240: Cardiovascular System | B240: PM0503 | C240: Reversible Causes of Cardiac Arrest
A241: Cardiovascular System | B241: PM0251 | C241: Important radiological signs in cardiology
A242: Cardiovascular System | B242: PM0203 | C242: Normal ECG waves and intervals
A243: Cardiovascular System | B243: PM0202 | C243: Augmented Unipolar Limb Leads
A244: Cardiovascular System | B244: PM0190 | C244: Adult Bradycardia with Pulse Algorithm
A245: Cardiovascular System | B245: PM0189 | C245: Adult Tachycardia with a Pulse Algorithm
A246: Cardiovascular System | B246: PM0170 | C246: Cardiac parameters
... A297: Nervous System | B297: PM0790 | C297: Causes of small and dilated pupils
A298: Nervous System | B298: PM0610 | C298: Contraindications for thrombolytic therapy | D298: Cardiovascular System
A299: Nervous System | B299: PM0603 | C299: Plasminogen activators (classification of fibrinolytics) | D299: Cardiovascular System
A300: Nervous System | B300: PM0404 | C300: Alzheimer’s disease
A301: Nervous System | B301: PM0123 | C301: Adverse effects of Phenytoin
A302: Nervous System | B302: PM0111 | C302: Types of Intracranial Hemorrhage
A303: Nervous System | B303: PM0063 | C303: Blood supply of Brain
A304: Blood Disorders | B304: PM2429 | C304: Causes of Thrombocytopenia
A305: Blood Disorders | B305: PM2423 | C305: Burkitt's Lymphoma
A306: Blood Disorders | B306: PM2420 | C306: Causes of Iron Deficiency Anemia
A307: Blood Disorders | B307: PM2419 | C307: Factors affecting iron absorption
A308: Blood Disorders | B308: PM2398 | C308: Classification of anti-platelet drugs
A309: Blood Disorders | B309: PM2385 | C309: Heparin vs. LMWH vs. Fondaparinux
A310: Blood Disorders | B310: PM2146 | C310: Differential Diagnosis of Microcytic Anaemia
A311: Blood Disorders | B311: PM2064 | C311: Thalassemia syndromes
... A345: Infectious Diseases | B345: PM1720 | C345: ATT Regimen for TB Patients
A346: Infectious Diseases | B346: PM1718 | C346: Diagnostic algorithm for Pulmonary TB — National Tuberculosis Elimination Programme (NTEP) 2020 Guidelines | D346: Respiratory System
A347: Infectious Diseases | B347: PM1717 | C347: AIDS-defining opportunistic infections and neoplasm
A348: Infectious Diseases | B348: PM1518 | C348: Indications of Ivermectin
A349: Infectious Diseases | B349: PM1516 | C349: Classification of antiretroviral drugs
A350: Infectious Diseases | B350: PM1271 | C350: Protein synthesis inhibitors: Primary subunit of ribosome binding
A351: Infectious Diseases | B351: PM1243 | C351: Cell wall synthesis inhibitors (mnemonic "BBC Van")
A352: Infectious Diseases | B352: PM0642 | C352: Acid resistant penicillins: mnemonic "VODKA"
A353: Infectious Diseases | B353: PM0594 | C353: 2021 NACO Guidelines on Post-exposure Prophylaxis (PEP) for HIV
A354: Infectious Diseases | B354: PM0039 | C354: Period of communicability of important diseases
A355: Acid -Base Regulation | B355: PM2409 | C355: Acid-Base Balance - Normal Values
A356: Acid -Base Regulation | B356: PM2098 | C356: Expected compensation in acid-base disorders
...

Sheet Surgery
A1: Subtopic | B1: Pearl ID | C1: Pearl | D1: Also listed under | E1: Note
A2: General Surgery | B2: PM2499 | C2: ATLS Primary Survey | D2: Trauma
A3: General Surgery | B3: PM2498 | C3: Suture materials
A4: General Surgery | B4: PM2459 | C4: Suture materials
A5: General Surgery | B5: PM2294 | C5: Ankle-brachial Pressure Index (ABPI)
A6: General Surgery | B6: PM2292 | C6: CEAP Classification of Chronic Lower Extremity Venous Disease
A7: General Surgery | B7: PM2290 | C7: Colloid solution
A8: General Surgery | B8: PM2289 | C8: Estimating maintenance fluid requirement - Holliday Segar formula
A9: General Surgery | B9: PM2171 | C9: Color Coding of Intravenous Cannulae
A10: General Surgery | B10: PM2166 | C10: Complications of total parenteral nutrition
A11: General Surgery | B11: PM2147 | C11: Modified Gilbert's classification of hernia
A12: General Surgery | B12: PM2142 | C12: Complications of enteral nutrition
A13: General Surgery | B13: PM2124 | C13: Drugs that should be discontinued prior to surgery
A14: General Surgery | B14: PM2120 | C14: Brilliantly Transilluminating Swellings
... A27: General Surgery | B27: PM1512 | C27: Identification of Surgical Retractors
A28: General Surgery | B28: PM1500 | C28: Gurd's criteria for diagnosing fat embolism syndrome | D28: Trauma
A29: General Surgery | B29: PM1492 | C29: Complications of a Massive Transfusion
A30: General Surgery | B30: PM1486 | C30: Classification of hemorrhagic shock
A31: General Surgery | B31: PM1478 | C31: Malnutrition Universal Screening Tool (MUST)
A32: General Surgery | B32: PM1313 | C32: Idiopathic/Immune thrombocytopenic purpura (ITP)
A33: General Surgery | B33: PM1292 | C33: Length of various structures in the human body
A34: General Surgery | B34: PM1112 | C34: Marjolin’s Ulcer
A35: General Surgery | B35: PM1047 | C35: The triangle of pain/Electrical hazard zone:
A36: General Surgery | B36: PM0794 | C36: Types of microcalcification indicating malignancy
A37: General Surgery | B37: PM0787 | C37: Clinical signs and symptoms of phaeochromocytoma
A38: General Surgery | B38: PM0487 | C38: Degrees of Burns
A39: General Surgery | B39: PM0478 | C39: Surgical wound classifications as defined by CDC
A40: General Surgery | B40: PM0476 | C40: Staging of Pressure Sores
... A93: Gastrointestinal & Abdominal Surgery | B93: PM1609 | C93: Complications following Pancreaticoduodenectomy
A94: Gastrointestinal & Abdominal Surgery | B94: PM1608 | C94: Presenting symptoms of periampullary tumors of pancreas | D94: Pancreatic Surgery
A95: Gastrointestinal & Abdominal Surgery | B95: PM1603 | C95: Revised Model for End-stage liver disease (MELD) scoring system: MELD 3.0
A96: Gastrointestinal & Abdominal Surgery | B96: PM1602 | C96: Child-Turcotte-Pugh Score
A97: Gastrointestinal & Abdominal Surgery | B97: PM1597 | C97: Difference between pyogenic and amebic liver abscess
A98: Gastrointestinal & Abdominal Surgery | B98: PM1588 | C98: Barium studies in GI tuberculosis
A99: Gastrointestinal & Abdominal Surgery | B99: PM1586 | C99: Factors Preventing Spontaneous Fistula Closure
A100: Gastrointestinal & Abdominal Surgery | B100: PM1585 | C100: Rule of two’s in Meckel's diverticulum
A101: Gastrointestinal & Abdominal Surgery | B101: PM1580 | C101: Characteristic differentiating features of the jejunum and ileum
A102: Gastrointestinal & Abdominal Surgery | B102: PM1578 | C102: Replacement conduits after esophagectomy
A103: Gastrointestinal & Abdominal Surgery | B103: PM1576 | C103: Types of Fundoplication
A104: Gastrointestinal & Abdominal Surgery | B104: PM1575 | C104: Manometric classification of esophageal motility disorders | D104: Upper GI Surgery
A105: Gastrointestinal & Abdominal Surgery | B105: PM1540 | C105: Charcot and Reynold's Triad
A106: Gastrointestinal & Abdominal Surgery | B106: PM1538 | C106: Courvoisier’s Law
A107: Gastrointestinal & Abdominal Surgery | B107: PM1537 | C107: Diagnostic Evaluation of the Gall Bladder
A108: Gastrointestinal & Abdominal Surgery | B108: PM1530 | C108: Mirizzi’s syndrome
A109: Gastrointestinal & Abdominal Surgery | B109: PM1528 | C109: Achalasia Cardia
A110: Gastrointestinal & Abdominal Surgery | B110: PM1527 | C110: Zenker’s Diverticulum
A111: Gastrointestinal & Abdominal Surgery | B111: PM1524 | C111: Diagnostic tests in Zollinger Ellison Syndrome
A112: Gastrointestinal & Abdominal Surgery | B112: PM1523 | C112: Types Of Gastric Ulcers
A113: Gastrointestinal & Abdominal Surgery | B113: PM1502 | C113: Types of Tracheo-esophageal Fistula/Esophageal Atresia
A114: Gastrointestinal & Abdominal Surgery | B114: PM1481 | C114: Hyperbilirubinemia- Causes
A115: Gastrointestinal & Abdominal Surgery | B115: PM1438 | C115: Types of Gallstones
A116: Gastrointestinal & Abdominal Surgery | B116: PM1415 | C116: Pancreatic Endocrine Neoplasms
... A122: Gastrointestinal & Abdominal Surgery | B122: PM1368 | C122: American Association for the Surgery of Trauma (AAST) Spleen Injury Scale
A123: Gastrointestinal & Abdominal Surgery | B123: PM1367 | C123: Post-Splenectomy Care | D123: Spleen & Pancreatic Surgery
A124: Gastrointestinal & Abdominal Surgery | B124: PM1366 | C124: Overwhelming Post-splenectomy Infection (OPSI)
A125: Gastrointestinal & Abdominal Surgery | B125: PM1320 | C125: Appendicular tumors and their characteristics
A126: Gastrointestinal & Abdominal Surgery | B126: PM1319 | C126: Complications of Appendicectomy
A127: Gastrointestinal & Abdominal Surgery | B127: PM1318 | C127: Oshner Sherren Regimen
A128: Gastrointestinal & Abdominal Surgery | B128: PM1317 | C128: Alvarado Scoring System
A129: Gastrointestinal & Abdominal Surgery | B129: PM1315 | C129: Signs in appendicitis
A130: Gastrointestinal & Abdominal Surgery | B130: PM1276 | C130: Chemotherapy for GI Tumours
A131: Gastrointestinal & Abdominal Surgery | B131: PM1269 | C131: Park's classification of fistula-in-ano
A132: Gastrointestinal & Abdominal Surgery | B132: PM1267 | C132: Grading of hemorrhoids
A133: Gastrointestinal & Abdominal Surgery | B133: PM1266 | C133: Differences between internal and external hemorrhoids
A134: Gastrointestinal & Abdominal Surgery | B134: PM1265 | C134: Features of anal canal above and below pectinate line
A135: Gastrointestinal & Abdominal Surgery | B135: PM1264 | C135: Risk Factors for Colorectal Cancer
... A178: Gastrointestinal & Abdominal Surgery | B178: PM0312 | C178: Opacities on a Plain Abdominal Radiograph that may be Confused with Renal Calculus
A179: Upper GI Surgery | B179: PM1575 | C179: Manometric classification of esophageal motility disorders | D179: Gastrointestinal & Abdominal Surgery
A180: Lower GI & Hernia Surgery | B180: PM1041 | C180: Difference between Direct and Indirect inguinal hernias:
A181: Spleen & Pancreatic Surgery | B181: PM1367 | C181: Post-Splenectomy Care | D181: Gastrointestinal & Abdominal Surgery
A182: Urology | B182: PM2286 | C182: Types of Cystitis
A183: Urology | B183: PM2278 | C183: Foley's Catheter
A184: Urology | B184: PM2277 | C184: WHO 2016 classification of testicular tumors
A185: Urology | B185: PM2259 | C185: Familial renal cell carcinoma syndromes
A186: Urology | B186: PM2252 | C186: Causes of Hydronephrosis
A187: Urology | B187: PM2238 | C187: American Association for the Surgery of Trauma (AAST) Kidney Injury Scale
A188: Urology | B188: PM2149 | C188: TNM staging of testicular tumour: American Joint Committee on Cancer (AJCC) and Union Internationale Contre le Cancer (UICC)
A189: Urology | B189: PM2123 | C189: IVU signs and associated conditions
A190: Urology | B190: PM2119 | C190: Most common testicular tumors
A191: Urology | B191: PM2081 | C191: Histologic subtypes of renal cell carcinoma
A192: Urology | B192: PM2068 | C192: Etiological Factors for Bladder Carcinoma
A193: Urology | B193: PM1220 | C193: Surgical shunts for ischaemic priapism
... A198: Urology | B198: PM0309 | C198: Radiolucent Renal Stones
A199: Trauma | B199: PM2499 | C199: ATLS Primary Survey | D199: General Surgery
A200: Trauma | B200: PM1500 | C200: Gurd's criteria for diagnosing fat embolism syndrome | D200: General Surgery
A201: Vascular Surgery | B201: PM2504 | C201: Two-level deep vein thrombosis (DVT) Wells score
A202: Vascular Surgery | B202: PM0559 | C202: Branches of the abdominal aorta
A203: Pancreatic Surgery | B203: PM1968 | C203: Pancreas - Most Commons
A204: Pancreatic Surgery | B204: PM1649 | C204: Surgical procedures for chronic pancreatitis
A205: Pancreatic Surgery | B205: PM1647 | C205: Resection and Hybrid Surgical Procedures for Chronic Pancreatitis
A206: Pancreatic Surgery | B206: PM1645 | C206: Chronic pancreatitis and pancreatic exocrine insufficiency: TIGAR-O classification system
A207: Pancreatic Surgery | B207: PM1644 | C207: Rosemont’s criteria for the diagnosis of chronic pancreatitis
A208: Pancreatic Surgery | B208: PM1641 | C208: Clinical Features of Chronic Pancreatitis
A209: Pancreatic Surgery | B209: PM1640 | C209: Pancreatic necrosis
A210: Pancreatic Surgery | B210: PM1639 | C210: Vascular complications of pancreatitis
A211: Pancreatic Surgery | B211: PM1636 | C211: SOFA and qSOFA Scores
A212: Pancreatic Surgery | B212: PM1635 | C212: Computed Tomography Severity Index (CTSI)/Balthazar Scoring for Acute Pancreatitis
... A218: Pancreatic Surgery | B218: PM1625 | C218: Causes of Acute Pancreatitis
A219: Pancreatic Surgery | B219: PM1608 | C219: Presenting symptoms of periampullary tumors of pancreas | D219: Gastrointestinal & Abdominal Surgery
A220: Pancreatic Surgery | B220: PM1606 | C220: Serous cystadenoma of the pancreas
...

Sheet Obstetrics and Gynaecology
A1: Subtopic | B1: Pearl ID | C1: Pearl | D1: Also listed under | E1: Note
A2: Fundamentals of Reproduction | B2: PM2366 | C2: Perineal Body
A3: Fundamentals of Reproduction | B3: PM2348 | C3: Homologous structures in male and female genitalia
A4: Fundamentals of Reproduction | B4: PM2338 | C4: Sexual Differentiation
A5: Fundamentals of Reproduction | B5: PM2182 | C5: Disorders of Sexual Development
A6: Fundamentals of Reproduction | B6: PM2104 | C6: Accessory Reproductive Glands in Male & Female
A7: Fundamentals of Reproduction | B7: PM1979 | C7: Derivatives of Mesonephric (Wolffian) duct and Paramesonephric (Mullerian) duct
A8: Fundamentals of Reproduction | B8: PM1912 | C8: Mullerian Anomalies
A9: Fundamentals of Reproduction | B9: PM1851 | C9: Fallopian tube
A10: Fundamentals of Reproduction | B10: PM1514 | C10: Hormonal Regulation of Menstrual Cycle
A11: Fundamentals of Reproduction | B11: PM1513 | C11: Events of Early Pregnancy
A12: Fundamentals of Reproduction | B12: PM1510 | C12: Biosynthesis Pathway for Androgen Synthesis
A13: Fundamentals of Reproduction | B13: PM1403 | C13: Fetal Skull Dimensions
... A53: Labor and Puerperium | B53: PM0041 | C53: Criteria for forceps delivery
A54: Labor and Puerperium | B54: PM0040 | C54: Obstetrics forceps | D54: Instruments
A55: Obstetric Complications | B55: PM2236 | C55: Twinning
A56: Obstetric Complications | B56: PM2225 | C56: Uses of Misoprostol
A57: Obstetric Complications | B57: PM2135 | C57: Radiological features of Intrauterine Death
A58: Obstetric Complications | B58: PM2131 | C58: Medical Termination of Pregnancy Act - MTP Act 1971
A59: Obstetric Complications | B59: PM1836 | C59: Twins
A60: Obstetric Complications | B60: PM1832 | C60: Complete vs. Partial Mole
A61: Obstetric Complications | B61: PM1829 | C61: Causes of oligohydramnios and polyhydramnios
A62: Obstetric Complications | B62: PM1822 | C62: Clinical classification of Spontaneous Abortion
A63: Obstetric Complications | B63: PM1441 | C63: Conditions Associated with Abnormal MSAFP
A64: Obstetric Complications | B64: PM1397 | C64: Indications of Amniotic Fluid Color
A65: Obstetric Complications | B65: PM1002 | C65: Contraindications to uterine artery embolization
A66: Medical and Surgical Complications in Pregnancy | B66: PM1003 | C66: Complications of pregnancy due to fibroids
... A128: Instruments | B128: PM2293 | C128: Instruments in OBG
A129: Instruments | B129: PM0040 | C129: Obstetrics forceps | D129: Labor and Puerperium
A130: Others | B130: PM2497 | C130: Uterine Signs in Pregnancy | E130: Title cut off in the screenshot; full title supplied by the user

Sheet Paediatrics
A1: Subtopic | B1: Pearl ID | C1: Pearl | D1: Also listed under | E1: Note
A2: Neonatology | B2: PM2490 | C2: Choice of initial feeding method in LBW infants
A3: Neonatology | B3: PM2394 | C3: A comprehensive list of factors that define an infant as being high risk
A4: Neonatology | B4: PM2213 | C4: Benign findings in a newborn
A5: Neonatology | B5: PM2195 | C5: APGAR score
A6: Neonatology | B6: PM2022 | C6: Teratogenic drugs and the birth defects
A7: Neonatology | B7: PM2021 | C7: Potential adverse reactions to drugs administered in infants
A8: Neonatology | B8: PM1828 | C8: Caput succedaneum and Cephalohematoma
A9: Neonatology | B9: PM1811 | C9: Timeline for primitive reflexes
A10: Neonatology | B10: PM1773 | C10: Baby-friendly hospital initiative (revised 2018)
A11: Growth and Development | B11: PM2090 | C11: Short stature: Familial vs Constitutional
A12: Growth and Development | B12: PM2037 | C12: Weight and height changes in children
A13: Growth and Development | B13: PM1946 | C13: Periods of growth
... A87: Paediatric Rheumatology | B87: PM0191 | C87: Kawasaki disease criteria
A88: Hematology | B88: PM2064 | C88: Thalassemia syndromes | E88: Partly cut off at the bottom of the screenshot

Sheet Orthopaedics
A1: Subtopic | B1: Pearl ID | C1: Pearl | D1: Also listed under | E1: Note
A2: Fracture and its complications | B2: PM2318 | C2: Bone grafts and substitutes
A3: Fracture and its complications | B3: PM2207 | C3: Acute Compartment and Crush Syndromes | D3: Complications of Fracture
A4: Fracture and its complications | B4: PM2164 | C4: Factors that impair bone healing and cause non-union | D4: Complications of Fracture
A5: Fracture and its complications | B5: PM2159 | C5: Orthopedic trauma and associated vascular injuries | D5: Upper Limb; Lower Limb
A6: Fracture and its complications | B6: PM2158 | C6: Fractures/dislocations and associated nerve injuries | D6: Upper Limb; Lower Limb; Nerve injuries
A7: Fracture and its complications | B7: PM2011 | C7: Plaster casts and their uses: | D7: Upper Limb
A8: Fracture and its complications | B8: PM1997 | C8: Gustilo and Anderson classification for open fracture
A9: Fracture and its complications | B9: PM1500 | C9: Gurd's criteria for diagnosing fat embolism syndrome
A10: Fracture and its complications | B10: PM0704 | C10: Types of Salter-Harris fractures- Mnemonic | D10: Upper Limb; Paediatric Orthopaedics
A11: Fracture and its complications | B11: PM0655 | C11: Pathological fracture
A12: Neck | B12: PM2041 | C12: Thoracic outlet syndrome and its tests:
A13: Neck | B13: PM0650 | C13: Torticollis
A14: Upper Limb | B14: PM2325 | C14: Methods of reduction of shoulder dislocation
A15: Upper Limb | B15: PM2324 | C15: Common dislocations at different joints | D15: Lower Limb
A16: Upper Limb | B16: PM2203 | C16: Important tests and signs to assess the function of rotator cuff muscles
A17: Upper Limb | B17: PM2159 | C17: Orthopedic trauma and associated vascular injuries | D17: Fracture and its complications; Lower Limb
A18: Upper Limb | B18: PM2158 | C18: Fractures/dislocations and associated nerve injuries | D18: Fracture and its complications; Lower Limb; Nerve injuries
A19: Upper Limb | B19: PM2125 | C19: Mechanisms of Injury around the elbow
A20: Upper Limb | B20: PM2053 | C20: Bursitis | D20: Lower Limb
A21: Upper Limb | B21: PM2052 | C21: Important conditions of the elbow:
A22: Upper Limb | B22: PM2033 | C22: Important Injuries of the Hand
A23: Upper Limb | B23: PM2016 | C23: Complications of Colle’s fracture:
A24: Upper Limb | B24: PM2015 | C24: Tension Band Wiring | D24: Lower Limb
A25: Upper Limb | B25: PM2014 | C25: Fractures of necessity | D25: Lower Limb
A26: Upper Limb | B26: PM2013 | C26: Three point bony relationship in elbow:
A27: Upper Limb | B27: PM2011 | C27: Plaster casts and their uses: | D27: Fracture and its complications
A28: Upper Limb | B28: PM2009 | C28: Tests for anterior shoulder dislocation
A29: Upper Limb | B29: PM2002 | C29: Dermatome of upper limb
A30: Upper Limb | B30: PM2001 | C30: Named classification systems for fractures and dislocations | D30: Lower Limb; Spine & Pelvis
A31: Upper Limb | B31: PM2000 | C31: Test for evaluation of glenohumeral joint instability in recurrent dislocation.
A32: Upper Limb | B32: PM1499 | C32: Compression neuropathies | D32: Lower Limb; Nerve injuries
A33: Upper Limb | B33: PM1418 | C33: Management of Pulseless Supracondylar Fracture | D33: Advanced Orthopaedics & Management
A34: Upper Limb | B34: PM1336 | C34: Common X-Ray views | D34: Lower Limb; Spine & Pelvis
A35: Upper Limb | B35: PM1099 | C35: Important angles used in the diagnosis of Orthopedic conditions | D35: Lower Limb; Spine & Pelvis
A36: Upper Limb | B36: PM0704 | C36: Types of Salter-Harris fractures- Mnemonic | D36: Fracture and its complications; Paediatric Orthopaedics
A37: Upper Limb | B37: PM0651 | C37: Medial and lateral epicondylitis
A38: Upper Limb | B38: PM0649 | C38: Named fractures of the upper limb
A39: Lower Limb | B39: PM2408 | C39: Anterior and posterior dislocation of the hip
A40: Lower Limb | B40: PM2324 | C40: Common dislocations at different joints | D40: Upper Limb
A41: Lower Limb | B41: PM2284 | C41: Movements and muscles tested - lower limb
A42: Lower Limb | B42: PM2221 | C42: Named fractures of the lower limb
A43: Lower Limb | B43: PM2202 | C43: Treatment of fracture neck of femur
A44: Lower Limb | B44: PM2178 | C44: Age wise treatment of fracture shaft of femur
A45: Lower Limb | B45: PM2170 | C45: Treatment of Genu Valgum
A46: Lower Limb | B46: PM2167 | C46: Primary and secondary deformities in Clubfoot
A47: Lower Limb | B47: PM2159 | C47: Orthopedic trauma and associated vascular injuries | D47: Fracture and its complications; Upper Limb
A48: Lower Limb | B48: PM2158 | C48: Fractures/dislocations and associated nerve injuries | D48: Fracture and its complications; Upper Limb; Nerve injuries
A49: Lower Limb | B49: PM2053 | C49: Bursitis | D49: Upper Limb
A50: Lower Limb | B50: PM2034 | C50: Osteochondritis
A51: Lower Limb | B51: PM2015 | C51: Tension Band Wiring | D51: Upper Limb
A52: Lower Limb | B52: PM2014 | C52: Fractures of necessity | D52: Upper Limb
A53: Lower Limb | B53: PM2001 | C53: Named classification systems for fractures and dislocations | D53: Upper Limb; Spine & Pelvis
A54: Lower Limb | B54: PM1499 | C54: Compression neuropathies | D54: Upper Limb; Nerve injuries
A55: Lower Limb | B55: PM1489 | C55: Commonly used splints and their indications | D55: Nerve injuries; Instruments in Orthopaedics
A56: Lower Limb | B56: PM1336 | C56: Common X-Ray views | D56: Upper Limb; Spine & Pelvis
A57: Lower Limb | B57: PM1099 | C57: Important angles used in the diagnosis of Orthopedic conditions | D57: Upper Limb; Spine & Pelvis
A58: Lower Limb | B58: PM0127 | C58: Unhappy triad of knee joint
A59: Lower Limb | B59: PM0035 | C59: Avascular Necrosis (AVN) | D59: Complications of Fracture
A60: Spine & Pelvis | B60: PM2127 | C60: Neurological examination in Intervertebral disc prolapse (IVDP)
A61: Spine & Pelvis | B61: PM2001 | C61: Named classification systems for fractures and dislocations | D61: Upper Limb; Lower Limb
A62: Spine & Pelvis | B62: PM1477 | C62: Named fractures of the vertebra
A63: Spine & Pelvis | B63: PM1448 | C63: Coxa Vara
A64: Spine & Pelvis | B64: PM1420 | C64: Delbet Classification of Hip Fractures in Children
A65: Spine & Pelvis | B65: PM1379 | C65: Ankylosing Spondylitis VS Diffuse idiopathic skeletal hyperostosis
A66: Spine & Pelvis | B66: PM1378 | C66: Important DD for Sacroiliitis in AS
A67: Spine & Pelvis | B67: PM1350 | C67: Differential Diagnosis of Lesions in Spine
A68: Spine & Pelvis | B68: PM1336 | C68: Common X-Ray views | D68: Upper Limb; Lower Limb
A69: Spine & Pelvis | B69: PM1189 | C69: Spondylolisthesis classification
A70: Spine & Pelvis | B70: PM1186 | C70: Classification of Congenital Scoliosis
A71: Spine & Pelvis | B71: PM1185 | C71: Whiplash Injury (Cervical Acceleration-Deceleration Injuries)
A72: Spine & Pelvis | B72: PM1182 | C72: Chance Fracture
A73: Spine & Pelvis | B73: PM1181 | C73: Column Theory of Spine
A74: Spine & Pelvis | B74: PM1099 | C74: Important angles used in the diagnosis of Orthopedic conditions | D74: Upper Limb; Lower Limb
A75: Spine & Pelvis | B75: PM1035 | C75: Bladder Injuries in Pelvic Fractures
A76: Spine & Pelvis | B76: PM1034 | C76: Spondylolisthesis
A77: Spine & Pelvis | B77: PM1031 | C77: Scheuermann Disease
A78: Spine & Pelvis | B78: PM1030 | C78: Surgery in Scoliosis
A79: Spine & Pelvis | B79: PM1028 | C79: Risser Sign
A80: Spine & Pelvis | B80: PM1022 | C80: SCIWORA
A81: Spine & Pelvis | B81: PM1021 | C81: Jefferson's Fracture
A82: Bone and Joint Infections | B82: PM0654 | C82: Septic arthritis
A83: Paediatric Orthopaedics | B83: PM2413 | C83: Age wise management of DDH
A84: Paediatric Orthopaedics | B84: PM2411 | C84: Age wise management of CTEV
A85: Paediatric Orthopaedics | B85: PM2296 | C85: Subtypes of Osteogenesis imperfecta
A86: Paediatric Orthopaedics | B86: PM2168 | C86: Order of correction of deformities in CTEV
... A94: Paediatric Orthopaedics | B94: PM1431 | C94: CTEV Procedures
A95: Paediatric Orthopaedics | B95: PM0704 | C95: Types of Salter-Harris fractures- Mnemonic | D95: Fracture and its complications; Upper Limb
A96: Metabolic Bone Diseases | B96: PM2198 | C96: Vitamin D activation and Rickets
A97: Metabolic Bone Diseases | B97: PM2197 | C97: Parathyroid Diseases
A98: Metabolic Bone Diseases | B98: PM2188 | C98: Risk factors for osteoporosis:
A99: Metabolic Bone Diseases | B99: PM2162 | C99: Bone turnover markers
A100: Metabolic Bone Diseases | B100: PM1988 | C100: Causes of lytic lesions in the skull
A101: Metabolic Bone Diseases | B101: PM1958 | C101: Z-score and T-score for osteoporosis:
A102: Metabolic Bone Diseases | B102: PM1859 | C102: Important differences between vitamin D and vitamin C deficiencies
A103: Metabolic Bone Diseases | B103: PM1613 | C103: Important Clinical Features of Rickets
A104: Metabolic Bone Diseases | B104: PM1599 | C104: Causes of Hypercalcemia
A105: Metabolic Bone Diseases | B105: PM1505 | C105: Summary of hormones that regulate Ca2+ levels
A106: Metabolic Bone Diseases | B106: PM1079 | C106: Biochemical parameters in metabolic bone diseases
A107: Metabolic Bone Diseases | B107: PM0540 | C107: Bone Formation and Bone Resorption Markers
...

Sheet Dermatology
A1: Subtopic | B1: Pearl ID | C1: Pearl | D1: Also listed under | E1: Note
A2: The Skin | B2: PM1889 | C2: Colour of Skin and Fitzpatrick Classification of Skin types
A3: The Skin | B3: PM1880 | C3: Cells of the epidermis
A4: The Skin | B4: PM1875 | C4: Dermoepidermal Junction/Basement Membrane Zone
A5: Clinical Dermatology | B5: PM2213 | C5: Benign findings in a newborn
A6: Clinical Dermatology | B6: PM1962 | C6: Flowchart for Quick Diagnosis using Tzanck Smear Results
A7: Clinical Dermatology | B7: PM1961 | C7: Tzanck Smear in Dermatology
A8: Clinical Dermatology | B8: PM0366 | C8: Difference between classic and neonatal scabies
A9: Clinical Dermatology | B9: PM0260 | C9: Wood's lamp examination
A10: Clinical Dermatology | B10: PM0257 | C10: Primary and Secondary Lesions of Skin
A11: Clinical Dermatology | B11: PM0256 | C11: Shapes of skin lesions
A12: Clinical Dermatology | B12: PM0255 | C12: Glossary of important skin lesions
A13: Clinical Dermatology | B13: PM0248 | C13: Key Chart to help differentiate lesions on face
... A32: Papulosquamous Disorders | B32: PM0259 | C32: Types of scales associated with dermatological conditions
A33: Vesiculobullous Disorders | B33: PM2455 | C33: Skin and soft tissue lesions caused by Staphylococcus | D33: Skin Infections & Infestations
A34: Vesiculobullous Disorders | B34: PM2454 | C34: Skin and soft tissue lesions caused by Streptococcus | D34: Skin Infections & Infestations
A35: Vesiculobullous Disorders | B35: PM2085 | C35: Differences between pemphigus vulgaris and bullous pemphigoid
A36: Vesiculobullous Disorders | B36: PM0363 | C36: Classification of Vesiculobullous Disorders
A37: Vesiculobullous Disorders | B37: PM0224 | C37: Vesiculobullous Disorders
A38: Skin Infections & Infestations | B38: PM2455 | C38: Skin and soft tissue lesions caused by Staphylococcus | D38: Vesiculobullous Disorders
A39: Skin Infections & Infestations | B39: PM2454 | C39: Skin and soft tissue lesions caused by Streptococcus | D39: Vesiculobullous Disorders
A40: Skin Infections & Infestations | B40: PM1995 | C40: Nail changes in lichen planus
A41: Skin Infections & Infestations | B41: PM1994 | C41: Nail changes in psoriasis
A42: Skin Infections & Infestations | B42: PM1971 | C42: Classification of cutaneous tuberculosis
A43: Skin Infections & Infestations | B43: PM1967 | C43: Characteristics of Ridley Jopling Classification in Leprosy
A44: Skin Infections & Infestations | B44: PM1966 | C44: Lepra Reactions
A45: Skin Infections & Infestations | B45: PM0618 | C45: Skin rashes: 1st to 6th diseases
A46: Skin Infections & Infestations | B46: PM0615 | C46: Clinical manifestations of herpes simplex virus-1
A47: Skin Infections & Infestations | B47: PM0360 | C47: Cutaneous Infections/Diseases caused by Staphylococcus aureus
A48: Skin Infections & Infestations | B48: PM0359 | C48: Cutaneous Infections/Diseases caused by Streptococcus pyogenes
A49: Skin Infections & Infestations | B49: PM0342 | C49: Differentiating features between Tuberculoid Leprosy (TT) and Lepromatous Leprosy (LL)
A50: Skin Infections & Infestations | B50: PM0341 | C50: WHO proposed Multi Drug Therapy (MDT) for the treatment of Leprosy
A51: Sexually Transmitted Infections | B51: PM2456 | C51: Sexually transmitted infections
... A63: Skin in Systemic Disorders | B63: PM0297 | C63: Types of Psoriatic Arthritis

Sheet Psychiatry
A1: Subtopic | B1: Pearl ID | C1: Pearl | D1: Also listed under | E1: Note
A2: Facets of Psychiatry | B2: PM2314 | C2: Scientists and their contributions to psychiatry
A3: Facets of Psychiatry | B3: PM0826 | C3: Maslow's Hierarchy of Needs
A4: Facets of Psychiatry | B4: PM0353 | C4: Defense mechanisms that operate in various diseases
A5: Facets of Psychiatry | B5: PM0351 | C5: Defense mechanisms
A6: Facets of Psychiatry | B6: PM0346 | C6: Contributions by Sigmund Freud
A7: Clinical Psychiatry | B7: PM2418 | C7: Actions of antipsychotic drugs
A8: Clinical Psychiatry | B8: PM2415 | C8: Adverse effects of specific antidepressants
A9: Clinical Psychiatry | B9: PM2384 | C9: Classification of disorders of thought
A10: Clinical Psychiatry | B10: PM2383 | C10: Disorders of thought and perception
A11: Clinical Psychiatry | B11: PM2323 | C11: ECT versus TMS
A12: Clinical Psychiatry | B12: PM2116 | C12: Neurotransmitters
A13: Clinical Psychiatry | B13: PM2046 | C13: The Mental Health Care Act, 2017 and The Mental Health Act, 1987
... A74: Child Psychiatry | B74: PM2030 | C74: Speech sound disorder Vs Neurological/Structural dysarthria
A75: Forensic Psychiatry | B75: PM2059 | C75: BNS section 22, M'Naghten's rule | E75: Title cut off in the screenshot; completed from the same pearl in Forensic Medicine

Sheet Anaesthesia
A1: Subtopic | B1: Pearl ID | C1: Pearl | D1: Also listed under | E1: Note
A2: Preoperative evaluation and monitoring | B2: PM2230 | C2: Factors affecting End-tidal CO2 (ETCO2)
A3: Preoperative evaluation and monitoring | B3: PM2124 | C3: Drugs that should be discontinued prior to surgery
A4: Preoperative evaluation and monitoring | B4: PM2093 | C4: Drugs that can be continued on the day of surgery
A5: Preoperative evaluation and monitoring | B5: PM0413 | C5: Samsoon & Young's Modified Mallampati Classification
A6: Preoperative evaluation and monitoring | B6: PM0412 | C6: Predictors of Difficult Airway
A7: Preoperative evaluation and monitoring | B7: PM0411 | C7: American Society of Anesthesiologists’ Physical Status Classification of Patients
A8: Preoperative evaluation and monitoring | B8: PM0186 | C8: Various capnography waveforms:
A9: Preoperative evaluation and monitoring | B9: PM0181 | C9: A list of anaesthetics and their physiological effects
A10: Preoperative evaluation and monitoring | B10: PM0139 | C10: Stages of Anesthesia
A11: Airway management and resuscitation | B11: PM2494 | C11: Basic Life Support (BLS) Algorithm
A12: Airway management and resuscitation | B12: PM2295 | C12: High quality CPR for adults
A13: Airway management and resuscitation | B13: PM2290 | C13: Colloid solution
... A53: Local and regional anaesthesia | B53: PM2276 | C53: Differences between Spinal and Epidural anesthesia
A54: Local and regional anaesthesia | B54: PM2275 | C54: Complications of neuraxial (spinal and epidural) anesthesia | D54: Complications of anaesthesia
A55: Local and regional anaesthesia | B55: PM2126 | C55: Factors affecting dermatomal spread of spinal anesthesia
A56: Local and regional anaesthesia | B56: PM2113 | C56: Nerve fibres & Their Properties
A57: Local and regional anaesthesia | B57: PM0532 | C57: Classification of Local Anesthetics based on the Potency
A58: Local and regional anaesthesia | B58: PM0531 | C58: Classification of local anesthetics based on duration of action
A59: Local and regional anaesthesia | B59: PM0513 | C59: High Yield Points in Local Anaesthetics
A60: Local and regional anaesthesia | B60: PM0510 | C60: Brachial Plexus Blocks
A61: Local and regional anaesthesia | B61: PM0489 | C61: Peripheral Nerve Classification and LA Sensitivity
A62: Local and regional anaesthesia | B62: PM0475 | C62: Absolute contraindications for Epidural
A63: Local and regional anaesthesia | B63: PM0469 | C63: Test Dose given in Epidural
A64: Local and regional anaesthesia | B64: PM0468 | C64: High yield points in epidural anaesthesia
A65: Local and regional anaesthesia | B65: PM0448 | C65: High Yield Points in spinal anesthesia
A66: Local and regional anaesthesia | B66: PM0447 | C66: Factors That Can Increase the Incidence of Headache After Spinal Puncture | D66: Complications of anaesthesia
A67: Local and regional anaesthesia | B67: PM0446 | C67: PDPH- Post-Dural Puncture Headache | D67: Complications of anaesthesia
A68: Local and regional anaesthesia | B68: PM0436 | C68: Order of block in spinal anaesthesia
A69: Local and regional anaesthesia | B69: PM0431 | C69: Important Root Values and Cranial Nerve Nuclei
A70: Local and regional anaesthesia | B70: PM0422 | C70: Maximum dose of local anaesthetics
A71: Local and regional anaesthesia | B71: PM0420 | C71: Systemic Absorbtion of Local Anaesthetic in the Order of Occurrence
A72: Local and regional anaesthesia | B72: PM0415 | C72: Classification of local anesthetics based on chemical structure
A73: Local and regional anaesthesia | B73: PM0036 | C73: Extent of important structures/spaces in the Spinal cord
A74: Anaesthesia in specific conditions | B74: PM0493 | C74: Anaesthetic drugs in patients with reduced renal function
A75: Anaesthesia in specific conditions | B75: PM0492 | C75: Coarctation of Aorta in Pregnancy
A76: Anaesthesia in specific conditions | B76: PM0485 | C76: High Yield Points in Pediatric Anesthesia
A77: Anaesthesia in specific conditions | B77: PM0484 | C77: Obstetric Anesthesia
A78: Anaesthesia in specific conditions | B78: PM0483 | C78: Obstetrics Indication for GA
A79: Anaesthesia in specific conditions | B79: PM0482 | C79: Regional Anesthesia in Obstetrics
... A81: Anaesthesia in specific conditions | B81: PM0398 | C81: Anesthetic Considerations in Patients with Aortic Stenosis
A82: Complications of anaesthesia | B82: PM2275 | C82: Complications of neuraxial (spinal and epidural) anesthesia | D82: Local and regional anaesthesia
A83: Complications of anaesthesia | B83: PM0447 | C83: Factors That Can Increase the Incidence of Headache After Spinal Puncture | D83: Local and regional anaesthesia
A84: Complications of anaesthesia | B84: PM0446 | C84: PDPH- Post-Dural Puncture Headache | D84: Local and regional anaesthesia
A85: Complications of anaesthesia | B85: PM0407 | C85: Complications and contraindications of retrobulbar block
A86: Complications of anaesthesia | B86: PM0406 | C86: Oculocardiac Reflex
A87: Complications of anaesthesia | B87: PM0403 | C87: Precautions during laser airway surgery
A88: Others | B88: PM2511 | C88: Environmental Effects of Inhaled Anesthetics
A89: Others | B89: PM0686 | C89: Opioid Receptors
A90: Others | B90: PM0624 | C90: Relative susceptibility of nerve fibres to conduction block by various agents
A91: Others | B91: PM0623 | C91: Types of mammalian nerve fibres (Erlanger and Gasser's classification)
A92: Others | B92: PM0534 | C92: Modified Bromage scale
A93: Others | B93: PM0494 | C93: Muscle Relaxant and Effect on Cardiac Muscarinic Receptors
A94: Others | B94: PM0471 | C94: Assessment of Pain
A95: Others | B95: PM0464 | C95: Indications of Mechanical Ventilation
A96: Others | B96: PM0432 | C96: Regarding Nerve Blockers
... A99: Others | B99: PM0184 | C99: Safety profiles of drugs

Sheet Radiology
A1: Subtopic | B1: Pearl ID | C1: Pearl | D1: Also listed under | E1: Note
A2: Must know X-Rays | B2: PM2086 | C2: Radiographic views of paranasal sinuses and mastoid
A3: Must know X-Rays | B3: PM1417 | C3: Radiographic views of temporal bone
A4: Must know X-Rays | B4: PM0645 | C4: Investigation of choice in Neurology
A5: Fundamentals of Radiology | B5: PM2500 | C5: Radionuclide agent and its uses
A6: Fundamentals of Radiology | B6: PM2380 | C6: Classification of iodinated contrast media:
A7: Fundamentals of Radiology | B7: PM1736 | C7: Half life of radio isotopes
A8: Fundamentals of Radiology | B8: PM0644 | C8: T1 vs T2 MRI
A9: Fundamentals of Radiology | B9: PM0283 | C9: Radionuclide agents and their uses
A10: Fundamentals of Radiology | B10: PM0048 | C10: Radioprotectors and Radiosensitizers
A11: Fundamentals of Radiology | B11: PM0047 | C11: Important SI units for radiation
A12: Fundamentals of Radiology | B12: PM0045 | C12: Ionising and penetrating ability of radiation
A13: Diagnostic Radiology | B13: PM2514 | C13: Radiological Appearance of Brain Tumours
... A41: Others | B41: PM2443 | C41: Barium Studies
